{
  "type": "Feature",
  "properties": {
    "gn:admin1_code":"DI",
    "gn:admin2_code":"3.0",
    "gn:asciiname":"Niederschlinder",
    "gn:country_code":"LU",
    "gn:dem":332,
    "gn:feature_class":"P",
    "gn:feature_code":"PPL",
    "gn:name":"Niederschlinder",
    "gn:population":0,
    "gn:timezone":"Europe/Luxembourg",
    "iso:country":"LU",
    "wof:name":"Niederschlinder",
    "wof:placetype":"locality"
},
  "geometry": {"coordinates":[6.06667,49.93333],"type":"Point"}
}