{
  "type": "Feature",
  "properties": {
    "iso:country":"LU",
    "name:deu_x_variant":[
        "Neumerl"
    ],
    "name:eng_x_preferred":[
        "Belair"
    ],
    "name:ltz_x_preferred":[
        "Belair"
    ],
    "name:ltz_x_variant":[
        "Neim\u00e4rel"
    ],
    "wof:name":"Belair",
    "wof:placetype":"neighbourhood"
},
  "geometry": {"coordinates":[6.10849372023978,49.61108109761748],"type":"Point"}
}