{
  "type": "Feature",
  "properties": {
    "iso:country":"LU",
    "name:deu_x_variant":[
        "Neumerl"
    ],
    "name:eng_x_preferred":[
        "Belair"
    ],
    "name:ltz_x_preferred":[
        "Belair"
    ],
    "name:ltz_x_variant":[
        "Neim\u00e4rel"
    ],
    "wof:lang_x_official":[
        "fra",
        "ltz",
        "deu"
    ],
    "wof:lang_x_spoken":[
        "fra",
        "ltz",
        "deu"
    ],
    "wof:name":"Belair",
    "wof:placetype":"neighbourhood"
},
  "geometry": {"coordinates":[6.108494,49.611081],"type":"Point"}
}