{
  "type": "Feature",
  "properties": {
    "gn:country":"LU",
    "gn:fcode":"PPL",
    "gn:population":1024,
    "iso:country":"LU",
    "name:cat_x_preferred":[
        "Mullendorf"
    ],
    "name:ceb_x_preferred":[
        "M\u00fcllendorf"
    ],
    "name:eng_x_preferred":[
        "Mullendorf"
    ],
    "name:fra_x_preferred":[
        "Mullendorf"
    ],
    "name:ltz_x_preferred":[
        "M\u00eblleref"
    ],
    "name:nld_x_preferred":[
        "M\u00fcllendorf"
    ],
    "name:pol_x_preferred":[
        "Mullendorf"
    ],
    "name:swe_x_preferred":[
        "M\u00fcllendorf"
    ],
    "name:und_x_variant":[
        "Muellendorf"
    ],
    "qs_pg:aaroncc":"LU",
    "qs_pg:gn_country":"LU",
    "qs_pg:gn_fcode":"PPL",
    "qs_pg:gn_pop":1024,
    "qs_pg:name":"M\u00fcllendorf",
    "qs_pg:name_adm0":"Luxembourg",
    "qs_pg:name_adm1":"Luxembourg",
    "qs_pg:photos_9r":0,
    "qs_pg:photos_sr":0,
    "qs_pg:pop_sr":3,
    "qs_pg:qs_pg_placetype":"locality",
    "qs_pg:qs_pg_placetype_gp":"Town",
    "qs_pg:woe_adm0":23424881,
    "woe:adm0_id":23424881,
    "woe:name_adm0":"Luxembourg",
    "woe:name_adm1":"Luxembourg",
    "woe:placetype":"Town",
    "wof:name":"M\u00fcllendorf",
    "wof:placetype":"neighbourhood",
    "wof:population":1024
},
  "geometry": {"coordinates":[6.13,49.68028],"type":"Point"}
}