{
  "type": "Feature",
  "properties": {
    "iso:country":"LU",
    "name:cat_x_preferred":[
        "Weimerskirch"
    ],
    "name:ceb_x_preferred":[
        "Weimerskirch"
    ],
    "name:deu_x_preferred":[
        "Weimerskirch"
    ],
    "name:eng_x_preferred":[
        "Weimerskirch"
    ],
    "name:fra_x_preferred":[
        "Weimerskirch"
    ],
    "name:ita_x_preferred":[
        "Weimerskirch"
    ],
    "name:ltz_x_preferred":[
        "Weimeschkierch"
    ],
    "name:nld_x_preferred":[
        "Weimerskirch"
    ],
    "name:swe_x_preferred":[
        "Weimerskirch"
    ],
    "name:und_x_variant":[
        "Neimersk"
    ],
    "qs:gn_adm0_cc":"LU",
    "qs:gn_fcode":"PPL",
    "qs:gn_local":2960316,
    "qs:gn_nam_loc":"Luxembourg, Luxembourg, Luxembourg, Luxembourg, LU",
    "qs:gn_namadm1":"03",
    "qs:gn_name":"Weimerskirch",
    "qs:local_max":27921,
    "qs:local_sum":40969,
    "qs:localhoods":14,
    "qs:name":"Neimersk",
    "qs:name_adm0":"Luxembourg",
    "qs:name_adm1":"Luxembourg",
    "qs:name_adm2":"Luxembourg",
    "qs:name_lau":"Luxembourg",
    "qs:name_local":"Luxembourg",
    "qs:photo_max":262,
    "qs:photo_sum":907,
    "qs:placetype":"Suburb",
    "qs:quad_count":30,
    "qs:woe_adm0":23424881,
    "qs:woe_adm1":20070560,
    "qs:woe_adm2":12591920,
    "qs:woe_lau":20075347,
    "qs:woe_local":979721,
    "qs:woe_ver":"7.10.0",
    "wof:lang":[
        "unk"
    ],
    "wof:lang_x_official":[
        "fra",
        "ltz",
        "deu"
    ],
    "wof:lang_x_spoken":[
        "fra",
        "ltz",
        "deu"
    ],
    "wof:name":"Neimersk",
    "wof:placetype":"neighbourhood"
},
  "geometry": {"coordinates":[6.123897,49.617853],"type":"Point"}
}