{
  "type": "Feature",
  "properties": {
    "gn:country":"LU",
    "gn:fcode":"PPLL",
    "gn:population":51,
    "iso:country":"LU",
    "name:cat_x_preferred":[
        "Pommerloch"
    ],
    "name:eng_x_preferred":[
        "Pommerloch"
    ],
    "name:fra_x_preferred":[
        "Pommerloch"
    ],
    "name:ltz_x_preferred":[
        "Pommerlach"
    ],
    "name:nld_x_preferred":[
        "Pommerloch"
    ],
    "name:und_x_variant":[
        "Reckingerhof"
    ],
    "qs_pg:aaroncc":"LU",
    "qs_pg:gn_country":"LU",
    "qs_pg:gn_fcode":"PPLL",
    "qs_pg:gn_pop":51,
    "qs_pg:name":"Pommerloch",
    "qs_pg:photos_9r":0,
    "qs_pg:photos_sr":0,
    "qs_pg:pop_sr":1,
    "qs_pg:qs_pg_placetype":"locality",
    "wof:name":"Pommerloch",
    "wof:placetype":"neighbourhood",
    "wof:population":51
},
  "geometry": {"coordinates":[5.86083,49.96028],"type":"Point"}
}