{
  "type": "Feature",
  "properties": {
    "gn:admin1_code":"DI",
    "gn:admin2_code":"11.0",
    "gn:asciiname":"Ober-Merzig",
    "gn:country_code":"LU",
    "gn:dem":347,
    "gn:feature_class":"P",
    "gn:feature_code":"PPL",
    "gn:name":"Ober-Merzig",
    "gn:population":0,
    "gn:timezone":"Europe/Luxembourg",
    "iso:country":"LU",
    "name:und_x_variant":[
        "Haut-Merzig",
        "Ober-Merzig"
    ],
    "wof:lang_x_official":[
        "fra",
        "ltz",
        "deu"
    ],
    "wof:lang_x_spoken":[
        "fra",
        "ltz",
        "deu"
    ],
    "wof:name":"Ober-Merzig",
    "wof:placetype":"neighbourhood"
},
  "geometry": {"coordinates":[6.01667,49.83333],"type":"Point"}
}