{
  "type": "Feature",
  "properties": {
    "gn:gn_country":"LU",
    "gn:gn_fcode":"PPL",
    "gn:gn_pop":299,
    "gn:population":299,
    "iso:country":"LU",
    "name:cat_x_preferred":[
        "Ellange"
    ],
    "name:ceb_x_preferred":[
        "Ellange"
    ],
    "name:eng_x_preferred":[
        "Ellange"
    ],
    "name:fra_x_preferred":[
        "Ellange"
    ],
    "name:ltz_x_preferred":[
        "Elleng"
    ],
    "name:nld_x_preferred":[
        "Ellange"
    ],
    "name:pol_x_preferred":[
        "Ellange"
    ],
    "name:swe_x_preferred":[
        "Ellange"
    ],
    "qs_pg:aaroncc":"LU",
    "qs_pg:gn_country":"LU",
    "qs_pg:gn_fcode":"PPL",
    "qs_pg:gn_pop":299,
    "qs_pg:name":"Ellange",
    "qs_pg:name_adm0":"Luxembourg",
    "qs_pg:name_adm1":"Grevenmacher",
    "qs_pg:photos":6,
    "qs_pg:photos_1k":1,
    "qs_pg:photos_9k":1,
    "qs_pg:photos_9r":1,
    "qs_pg:photos_all":6,
    "qs_pg:photos_sr":1,
    "qs_pg:pop_sr":2,
    "qs_pg:qs_pg_placetype":"locality",
    "qs_pg:qs_pg_placetype_gp":"Town",
    "qs_pg:woe_adm0":23424881,
    "woe:adm0_id":23424881,
    "woe:name_adm0":"Luxembourg",
    "woe:name_adm1":"Grevenmacher",
    "woe:placetype":"Town",
    "wof:name":"Ellange",
    "wof:placetype":"locality",
    "wof:population":299
},
  "geometry": {"coordinates":[6.29833,49.52],"type":"Point"}
}