{
  "type": "Feature",
  "properties": {
    "gn:country":"LU",
    "gn:fcode":"PPL",
    "gn:population":146,
    "iso:country":"LU",
    "name:cat_x_preferred":[
        "Doennange"
    ],
    "name:ceb_x_preferred":[
        "Doennange"
    ],
    "name:deu_x_preferred":[
        "D\u00f6nningen"
    ],
    "name:eng_x_preferred":[
        "Doennange"
    ],
    "name:fra_x_preferred":[
        "Doennange"
    ],
    "name:ltz_x_preferred":[
        "Di\u00e4njen"
    ],
    "name:msa_x_preferred":[
        "Doennange"
    ],
    "name:nld_x_preferred":[
        "Doennange"
    ],
    "name:pol_x_preferred":[
        "Doennange"
    ],
    "name:swe_x_preferred":[
        "Doennange"
    ],
    "name:und_x_variant":[
        "Doeningen"
    ],
    "qs_pg:aaroncc":"LU",
    "qs_pg:gn_country":"LU",
    "qs_pg:gn_fcode":"PPL",
    "qs_pg:gn_pop":146,
    "qs_pg:name":"Doennange",
    "qs_pg:name_adm0":"Luxembourg",
    "qs_pg:name_adm1":"Diekirch",
    "qs_pg:photos_9k":1,
    "qs_pg:photos_9r":2,
    "qs_pg:photos_all":50,
    "qs_pg:photos_sr":0,
    "qs_pg:pop_sr":1,
    "qs_pg:qs_pg_placetype":"locality",
    "qs_pg:qs_pg_placetype_gp":"Town",
    "qs_pg:woe_adm0":23424881,
    "woe:adm0_id":23424881,
    "woe:name_adm0":"Luxembourg",
    "woe:name_adm1":"Diekirch",
    "woe:placetype":"Town",
    "wof:name":"Doennange",
    "wof:placetype":"neighbourhood",
    "wof:population":146
},
  "geometry": {"coordinates":[5.95583,50.06222],"type":"Point"}
}