{
  "type": "Feature",
  "properties": {
    "gn:country":"LU",
    "gn:fcode":"PPL",
    "gn:population":2522,
    "iso:country":"LU",
    "name:bel_x_preferred":[
        "\u0421\u0430\u043d\u0434\u0432\u0435\u0439\u043b\u0435\u0440"
    ],
    "name:bul_x_preferred":[
        "\u0421\u0430\u043d\u0434\u0432\u0430\u0439\u043b\u0435\u0440"
    ],
    "name:bul_x_variant":[
        "\u0421\u0430\u043d\u0434\u0432\u0435\u0439\u043b\u0435\u0440"
    ],
    "name:cat_x_preferred":[
        "Sandweiler"
    ],
    "name:ceb_x_preferred":[
        "Sandweiler"
    ],
    "name:dan_x_preferred":[
        "Sandweiler"
    ],
    "name:deu_x_preferred":[
        "Sandweiler"
    ],
    "name:eng_x_preferred":[
        "Sandweiler"
    ],
    "name:fas_x_preferred":[
        "\u0633\u0646\u062f\u0648\u0627\u06cc\u0644\u0631"
    ],
    "name:fra_x_preferred":[
        "Sandweiler"
    ],
    "name:gsw_x_preferred":[
        "Sandweiler"
    ],
    "name:hun_x_preferred":[
        "Sandweiler"
    ],
    "name:ita_x_preferred":[
        "Sandweiler"
    ],
    "name:jpn_x_preferred":[
        "\u30b5\u30f3\u30c9\u30a6\u30a7\u30a4\u30e9\u30fc"
    ],
    "name:ltz_x_preferred":[
        "Gemeng Sandweiler"
    ],
    "name:ltz_x_variant":[
        "Sandweiler"
    ],
    "name:mkd_x_preferred":[
        "\u0421\u0430\u043d\u0434\u0432\u0435\u0458\u043b\u0435\u0440"
    ],
    "name:msa_x_preferred":[
        "Sandweiler"
    ],
    "name:nan_x_preferred":[
        "Sandweiler"
    ],
    "name:nld_x_preferred":[
        "Sandweiler"
    ],
    "name:nob_x_preferred":[
        "Sandweiler"
    ],
    "name:pol_x_preferred":[
        "Sandweiler"
    ],
    "name:por_x_preferred":[
        "Sandweiler"
    ],
    "name:rus_x_preferred":[
        "\u0421\u0430\u043d\u0434\u0432\u0435\u0439\u043b\u0435\u0440"
    ],
    "name:slk_x_preferred":[
        "Sandweiler"
    ],
    "name:spa_x_preferred":[
        "Sandweiler"
    ],
    "name:swe_x_preferred":[
        "Sandweiler"
    ],
    "name:ukr_x_preferred":[
        "\u0421\u0430\u043d\u0434\u0432\u0430\u0439\u043b\u0435\u0440"
    ],
    "qs_pg:aaroncc":"LU",
    "qs_pg:gn_country":"LU",
    "qs_pg:gn_fcode":"PPL",
    "qs_pg:gn_pop":2522,
    "qs_pg:name":"Sandweiler",
    "qs_pg:name_adm0":"Luxembourg",
    "qs_pg:name_adm1":"Luxembourg",
    "qs_pg:photos":37,
    "qs_pg:photos_1k":7,
    "qs_pg:photos_9k":1,
    "qs_pg:photos_9r":2,
    "qs_pg:photos_all":37,
    "qs_pg:photos_sr":2,
    "qs_pg:pop_sr":4,
    "qs_pg:qs_pg_placetype":"locality",
    "qs_pg:qs_pg_placetype_gp":"Town",
    "qs_pg:woe_adm0":23424881,
    "woe:adm0_id":23424881,
    "woe:name_adm0":"Luxembourg",
    "woe:name_adm1":"Luxembourg",
    "woe:placetype":"Town",
    "wof:name":"Sandweiler",
    "wof:placetype":"locality",
    "wof:population":2522
},
  "geometry": {"coordinates":[6.21889,49.61333],"type":"Point"}
}