{
  "type": "Feature",
  "properties": {
    "gn:country":"LU",
    "gn:fcode":"PPL",
    "gn:population":142,
    "iso:country":"LU",
    "name:cat_x_preferred":[
        "Lellig"
    ],
    "name:ceb_x_preferred":[
        "Lellig"
    ],
    "name:deu_x_preferred":[
        "Lellig"
    ],
    "name:eng_x_preferred":[
        "Lellig"
    ],
    "name:fra_x_preferred":[
        "Lellig"
    ],
    "name:ltz_x_preferred":[
        "Lelleg"
    ],
    "name:msa_x_preferred":[
        "Lellig"
    ],
    "name:nld_x_preferred":[
        "Lellig"
    ],
    "name:pol_x_preferred":[
        "Lellig"
    ],
    "name:swe_x_preferred":[
        "Lellig"
    ],
    "qs_pg:aaroncc":"LU",
    "qs_pg:gn_country":"LU",
    "qs_pg:gn_fcode":"PPL",
    "qs_pg:gn_pop":142,
    "qs_pg:name":"Lellig",
    "qs_pg:name_adm0":"Luxembourg",
    "qs_pg:name_adm1":"Grevenmacher",
    "qs_pg:photos_9k":1,
    "qs_pg:photos_9r":3,
    "qs_pg:photos_all":123,
    "qs_pg:photos_sr":0,
    "qs_pg:pop_sr":1,
    "qs_pg:qs_pg_placetype":"locality",
    "qs_pg:qs_pg_placetype_gp":"Town",
    "qs_pg:woe_adm0":23424881,
    "woe:adm0_id":23424881,
    "woe:name_adm0":"Luxembourg",
    "woe:name_adm1":"Grevenmacher",
    "woe:placetype":"Town",
    "wof:lang_x_official":[
        "fra",
        "ltz",
        "deu"
    ],
    "wof:lang_x_spoken":[
        "fra",
        "ltz",
        "deu"
    ],
    "wof:name":"Lellig",
    "wof:placetype":"neighbourhood",
    "wof:population":142
},
  "geometry": {"coordinates":[6.43639,49.71611],"type":"Point"}
}