{
  "type": "Feature",
  "properties": {
    "gn:country":"LU",
    "gn:fcode":"PPL",
    "gn:population":43,
    "iso:country":"LU",
    "name:cat_x_preferred":[
        "Levelange"
    ],
    "name:eng_x_preferred":[
        "Levelange"
    ],
    "name:fra_x_preferred":[
        "Levelange"
    ],
    "name:ltz_x_preferred":[
        "Liewel"
    ],
    "name:nld_x_preferred":[
        "Levelange"
    ],
    "qs_pg:aaroncc":"LU",
    "qs_pg:gn_country":"LU",
    "qs_pg:gn_fcode":"PPL",
    "qs_pg:gn_pop":43,
    "qs_pg:name":"Levelange",
    "qs_pg:name_adm0":"Luxembourg",
    "qs_pg:name_adm1":"Diekirch",
    "qs_pg:photos_9r":0,
    "qs_pg:photos_sr":0,
    "qs_pg:pop_sr":1,
    "qs_pg:qs_pg_placetype":"locality",
    "qs_pg:qs_pg_placetype_gp":"Town",
    "qs_pg:woe_adm0":23424881,
    "woe:adm0_id":23424881,
    "woe:name_adm0":"Luxembourg",
    "woe:name_adm1":"Diekirch",
    "woe:placetype":"Town",
    "wof:lang_x_official":[
        "fra",
        "ltz",
        "deu"
    ],
    "wof:lang_x_spoken":[
        "fra",
        "ltz",
        "deu"
    ],
    "wof:name":"Levelange",
    "wof:placetype":"neighbourhood",
    "wof:population":43
},
  "geometry": {"coordinates":[5.85667,49.73972],"type":"Point"}
}