{
  "type": "Feature",
  "properties": {
    "gn:population":416,
    "iso:country":"LU",
    "name:bel_x_preferred":[
        "\u0412\u0430\u043b\u044c\u0434\u0431\u0440\u044d\u0434\u0437\u0456\u043c\u044e"
    ],
    "name:cat_x_preferred":[
        "Waldbredimus"
    ],
    "name:dan_x_preferred":[
        "Waldbredimus"
    ],
    "name:deu_x_preferred":[
        "Waldbredimus"
    ],
    "name:eng_x_preferred":[
        "Waldbredimus"
    ],
    "name:fas_x_preferred":[
        "\u0648\u0627\u0644\u062f\u0628\u0631\u062f\u06cc\u0645\u0648\u0633"
    ],
    "name:fra_x_preferred":[
        "Waldbredimus"
    ],
    "name:gsw_x_preferred":[
        "Waldbriedemes"
    ],
    "name:ita_x_preferred":[
        "Waldbredimus"
    ],
    "name:ltz_x_preferred":[
        "Gemeng Waldbriedemes"
    ],
    "name:msa_x_preferred":[
        "Waldbredimus"
    ],
    "name:nan_x_preferred":[
        "Waldbredimus"
    ],
    "name:nld_x_preferred":[
        "Waldbredimus"
    ],
    "name:nob_x_preferred":[
        "Waldbredimus"
    ],
    "name:pol_x_preferred":[
        "Waldbredimus"
    ],
    "name:por_x_preferred":[
        "Waldbredimus"
    ],
    "name:rus_x_preferred":[
        "\u0412\u0430\u043b\u044c\u0434\u0431\u0440\u0435\u0434\u0438\u043c\u044e"
    ],
    "name:slk_x_preferred":[
        "Waldbredimus"
    ],
    "name:swe_x_preferred":[
        "Waldbredimus"
    ],
    "name:ukr_x_preferred":[
        "\u0412\u0430\u043b\u044c\u0434\u0431\u0440\u0435\u0434\u0456\u043c\u044e"
    ],
    "name:und_x_preferred":[
        "Waldbredimus"
    ],
    "qs:a0":"Luxembourg",
    "qs:a1":"*",
    "qs:a1r":"0",
    "qs:adm0":"Luxembourg",
    "qs:la_lc":"*",
    "qs:level":"locality",
    "qs:loc":"Waldbredimus",
    "qs:loc_alt":"Waldbredimus",
    "qs:pop":0,
    "qs:type":"buffered point",
    "wof:lang":[
        "unk"
    ],
    "wof:name":"Waldbredimus",
    "wof:placetype":"locality",
    "wof:population":416
},
  "geometry": {"coordinates":[6.285597,49.555981],"type":"Point"}
}