{
  "type": "Feature",
  "properties": {
    "gn:admin1_code":"DI",
    "gn:admin2_code":"2.0",
    "gn:asciiname":"Gruef",
    "gn:cc2":"LU",
    "gn:country_code":"LU",
    "gn:dem":219,
    "gn:feature_class":"P",
    "gn:feature_code":"PPLL",
    "gn:name":"Gruef",
    "gn:population":0,
    "gn:timezone":"Europe/Luxembourg",
    "iso:country":"LU",
    "name:und_x_variant":[
        "Grof",
        "Gruef"
    ],
    "wof:name":"Gruef",
    "wof:placetype":"locality"
},
  "geometry": {"coordinates":[6.22194,49.88028],"type":"Point"}
}