{
  "type": "Feature",
  "properties": {
    "gn:gn_country":"LU",
    "gn:gn_fcode":"PPL",
    "gn:gn_pop":114,
    "gn:population":114,
    "iso:country":"LU",
    "name:unk_x_variant":[
        "Fischbach"
    ],
    "qs_pg:aaroncc":"LU",
    "qs_pg:gn_country":"LU",
    "qs_pg:gn_fcode":"PPL",
    "qs_pg:gn_pop":114,
    "qs_pg:name":"Fischbach-l\u00e8s-Clervaux",
    "qs_pg:name_adm0":"Luxembourg",
    "qs_pg:name_adm1":"Diekirch",
    "qs_pg:photos_9r":0,
    "qs_pg:photos_sr":0,
    "qs_pg:pop_sr":1,
    "qs_pg:qs_pg_placetype":"locality",
    "qs_pg:qs_pg_placetype_gp":"Town",
    "qs_pg:woe_adm0":23424881,
    "woe:adm0_id":23424881,
    "woe:name_adm0":"Luxembourg",
    "woe:name_adm1":"Diekirch",
    "woe:placetype":"Town",
    "wof:name":"Fischbach-l\u00e8s-Clervaux",
    "wof:placetype":"locality",
    "wof:population":114
},
  "geometry": {"coordinates":[6.06889,50.07528],"type":"Point"}
}