{
  "type": "Feature",
  "properties": {
    "gn:admin1_code":"GR",
    "gn:admin2_code":"4.0",
    "gn:asciiname":"Fronay",
    "gn:country_code":"LU",
    "gn:dem":262,
    "gn:feature_class":"P",
    "gn:feature_code":"PPL",
    "gn:name":"Fronay",
    "gn:population":0,
    "gn:timezone":"Europe/Luxembourg",
    "iso:country":"LU",
    "name:und_x_variant":[
        "Ferme Fronay",
        "Fronayhof",
        "Fronay"
    ],
    "wof:name":"Fronay",
    "wof:placetype":"locality"
},
  "geometry": {"coordinates":[6.41667,49.66667],"type":"Point"}
}