{
  "type": "Feature",
  "properties": {
    "gn:admin1_code":"WI",
    "gn:admin2_code":"5.0",
    "gn:asciiname":"Dunkrodt",
    "gn:country_code":"LU",
    "gn:dem":373,
    "gn:feature_class":"P",
    "gn:feature_code":"PPLL",
    "gn:name":"Dunkrodt",
    "gn:population":0,
    "gn:timezone":"Europe/Luxembourg",
    "iso:country":"LU",
    "wof:name":"Dunkrodt",
    "wof:placetype":"locality"
},
  "geometry": {"coordinates":[5.87861,49.92306],"type":"Point"}
}