{
  "type": "Feature",
  "properties": {
    "gn:admin1_code":"RD",
    "gn:admin2_code":"6.0",
    "gn:asciiname":"Loorbierg",
    "gn:cc2":"LU",
    "gn:country_code":"LU",
    "gn:dem":421,
    "gn:feature_class":"P",
    "gn:feature_code":"PPLL",
    "gn:name":"Loorbierg",
    "gn:population":0,
    "gn:timezone":"Europe/Luxembourg",
    "iso:country":"LU",
    "name:und_x_variant":[
        "Brucherhof",
        "Loreshof",
        "Loringshof",
        "Ferme Loring",
        "Loorbierg"
    ],
    "wof:lang_x_official":[
        "fra",
        "ltz",
        "deu"
    ],
    "wof:lang_x_spoken":[
        "fra",
        "ltz",
        "deu"
    ],
    "wof:name":"Loorbierg",
    "wof:placetype":"neighbourhood"
},
  "geometry": {"coordinates":[5.85111,49.85944],"type":"Point"}
}