{
  "type": "Feature",
  "properties": {
    "gn:gn_country":"LU",
    "gn:gn_fcode":"PPL",
    "gn:gn_pop":2225,
    "gn:population":2225,
    "iso:country":"LU",
    "name:bar_x_preferred":[
        "Steinfort"
    ],
    "name:bel_x_preferred":[
        "\u0428\u0442\u044d\u0439\u043d\u0444\u0430\u0440\u0442"
    ],
    "name:cat_x_preferred":[
        "Steinfort"
    ],
    "name:ces_x_preferred":[
        "Steinfort"
    ],
    "name:dan_x_preferred":[
        "Steinfort"
    ],
    "name:deu_x_preferred":[
        "Steinfort"
    ],
    "name:eng_x_preferred":[
        "Steinfort"
    ],
    "name:fas_x_preferred":[
        "\u0627\u0634\u062a\u0627\u06cc\u0646\u0641\u0648\u0631\u062a\u060c \u0644\u0648\u06a9\u0632\u0627\u0645\u0628\u0648\u0631\u06af"
    ],
    "name:fra_x_preferred":[
        "Steinfort"
    ],
    "name:gsw_x_preferred":[
        "Stengefort"
    ],
    "name:hun_x_preferred":[
        "Steinfort"
    ],
    "name:ita_x_preferred":[
        "Steinfort"
    ],
    "name:lit_x_preferred":[
        "\u0160teinfortas"
    ],
    "name:ltz_x_preferred":[
        "Stengefort"
    ],
    "name:msa_x_preferred":[
        "Steinfort"
    ],
    "name:nld_x_preferred":[
        "Steinfort"
    ],
    "name:nob_x_preferred":[
        "Steinfort"
    ],
    "name:pol_x_preferred":[
        "Steinfort"
    ],
    "name:por_x_preferred":[
        "Steinfort"
    ],
    "name:rus_x_preferred":[
        "\u0428\u0442\u0435\u0439\u043d\u0444\u043e\u0440\u0442"
    ],
    "name:slk_x_preferred":[
        "Steinfort"
    ],
    "name:swe_x_preferred":[
        "Steinfort"
    ],
    "name:ukr_x_preferred":[
        "\u0428\u0442\u0430\u0439\u043d\u0444\u043e\u0440\u0442"
    ],
    "qs_pg:aaroncc":"LU",
    "qs_pg:gn_country":"LU",
    "qs_pg:gn_fcode":"PPL",
    "qs_pg:gn_pop":2225,
    "qs_pg:name":"Steinfort",
    "qs_pg:name_adm0":"Luxembourg",
    "qs_pg:name_adm1":"Luxembourg",
    "qs_pg:photos":45,
    "qs_pg:photos_1k":9,
    "qs_pg:photos_9k":1,
    "qs_pg:photos_9r":2,
    "qs_pg:photos_all":45,
    "qs_pg:photos_sr":2,
    "qs_pg:pop_sr":4,
    "qs_pg:qs_pg_placetype":"locality",
    "qs_pg:qs_pg_placetype_gp":"Town",
    "qs_pg:woe_adm0":23424881,
    "woe:adm0_id":23424881,
    "woe:name_adm0":"Luxembourg",
    "woe:name_adm1":"Luxembourg",
    "woe:placetype":"Town",
    "wof:name":"Steinfort",
    "wof:placetype":"locality",
    "wof:population":2225
},
  "geometry": {"coordinates":[5.91917,49.66139],"type":"Point"}
}