{
  "type": "Feature",
  "properties": {
    "gn:country":"LU",
    "gn:fcode":"PPL",
    "gn:population":319,
    "iso:country":"LU",
    "name:bar_x_preferred":[
        "Hoscheid"
    ],
    "name:bel_x_preferred":[
        "\u0425\u043e\u0448\u044d\u0439\u0434"
    ],
    "name:cat_x_preferred":[
        "Hoscheid"
    ],
    "name:ceb_x_preferred":[
        "Hoscheid"
    ],
    "name:dan_x_preferred":[
        "Hoscheid"
    ],
    "name:deu_x_preferred":[
        "Hoscheid"
    ],
    "name:eng_x_preferred":[
        "Hoscheid"
    ],
    "name:fra_x_preferred":[
        "Hoscheid"
    ],
    "name:gsw_x_preferred":[
        "Houschent"
    ],
    "name:ita_x_preferred":[
        "Hoscheid"
    ],
    "name:lim_x_preferred":[
        "Hoscheid"
    ],
    "name:ltz_x_preferred":[
        "Gemeng Houschent"
    ],
    "name:nan_x_preferred":[
        "Hoscheid"
    ],
    "name:nld_x_preferred":[
        "Hoscheid"
    ],
    "name:nob_x_preferred":[
        "Hoscheid"
    ],
    "name:pol_x_preferred":[
        "Hoscheid"
    ],
    "name:por_x_preferred":[
        "Hoscheid"
    ],
    "name:rus_x_preferred":[
        "\u0425\u043e\u0448\u0435\u0439\u0434"
    ],
    "name:slk_x_preferred":[
        "Hoscheid"
    ],
    "name:swe_x_preferred":[
        "Hoscheid"
    ],
    "name:ukr_x_preferred":[
        "\u0425\u043e\u0448\u0430\u0439\u0434"
    ],
    "name:und_x_variant":[
        "Hohscheid"
    ],
    "qs_pg:aaroncc":"LU",
    "qs_pg:gn_country":"LU",
    "qs_pg:gn_fcode":"PPL",
    "qs_pg:gn_pop":319,
    "qs_pg:name":"Hoscheid",
    "qs_pg:name_adm0":"Luxembourg",
    "qs_pg:name_adm1":"Diekirch",
    "qs_pg:photos":26,
    "qs_pg:photos_1k":5,
    "qs_pg:photos_9k":1,
    "qs_pg:photos_9r":2,
    "qs_pg:photos_all":26,
    "qs_pg:photos_sr":2,
    "qs_pg:pop_sr":2,
    "qs_pg:qs_pg_placetype":"locality",
    "qs_pg:qs_pg_placetype_gp":"Town",
    "qs_pg:woe_adm0":23424881,
    "woe:adm0_id":23424881,
    "woe:name_adm0":"Luxembourg",
    "woe:name_adm1":"Diekirch",
    "woe:placetype":"Town",
    "wof:lang_x_official":[
        "fra",
        "ltz",
        "deu"
    ],
    "wof:lang_x_spoken":[
        "fra",
        "ltz",
        "deu"
    ],
    "wof:name":"Hoscheid",
    "wof:placetype":"neighbourhood",
    "wof:population":319
},
  "geometry": {"coordinates":[6.08167,49.94722],"type":"Point"}
}