{
  "type": "Feature",
  "properties": {
    "gn:gn_country":"LU",
    "gn:gn_fcode":"PPL",
    "gn:gn_pop":3627,
    "gn:population":3627,
    "iso:country":"LU",
    "name:cat_x_preferred":[
        "Bereldange"
    ],
    "name:chi_x_preferred":[
        "\u8c9d\u52d2\u767b\u683c"
    ],
    "name:dut_x_preferred":[
        "Bereldange"
    ],
    "name:eng_x_preferred":[
        "Bereldange"
    ],
    "name:fre_x_preferred":[
        "Bereldange"
    ],
    "name:ger_x_preferred":[
        "Bereldingen"
    ],
    "name:ltz_x_preferred":[
        "B\u00e4reldeng"
    ],
    "name:pol_x_preferred":[
        "Bereldange"
    ],
    "name:unk_x_variant":[
        "B\u00e9reldange"
    ],
    "qs_pg:aaroncc":"LU",
    "qs_pg:gn_country":"LU",
    "qs_pg:gn_fcode":"PPL",
    "qs_pg:gn_pop":3627,
    "qs_pg:name":"Bereldange",
    "qs_pg:name_adm0":"Luxembourg",
    "qs_pg:name_adm1":"Luxembourg",
    "qs_pg:photos_9k":1,
    "qs_pg:photos_9r":1,
    "qs_pg:photos_all":9,
    "qs_pg:photos_sr":0,
    "qs_pg:pop_sr":4,
    "qs_pg:qs_pg_placetype":"locality",
    "qs_pg:qs_pg_placetype_gp":"Town",
    "qs_pg:woe_adm0":23424881,
    "woe:adm0_id":23424881,
    "woe:name_adm0":"Luxembourg",
    "woe:name_adm1":"Luxembourg",
    "woe:placetype":"Town",
    "wof:name":"Bereldange",
    "wof:placetype":"locality",
    "wof:population":3627
},
  "geometry": {"coordinates":[6.1275,49.65694],"type":"Point"}
}