{
  "type": "Feature",
  "properties": {
    "gn:admin1_code":"RD",
    "gn:admin2_code":"5.0",
    "gn:asciiname":"Maison Klein",
    "gn:country_code":"LU",
    "gn:dem":304,
    "gn:feature_class":"P",
    "gn:feature_code":"PPL",
    "gn:name":"Maison Klein",
    "gn:population":0,
    "gn:timezone":"Europe/Luxembourg",
    "iso:country":"LU",
    "wof:lang_x_official":[
        "fra",
        "ltz",
        "deu"
    ],
    "wof:lang_x_spoken":[
        "fra",
        "ltz",
        "deu"
    ],
    "wof:name":"Maison Klein",
    "wof:placetype":"neighbourhood"
},
  "geometry": {"coordinates":[5.85,49.75],"type":"Point"}
}