{
  "type": "Feature",
  "properties": {
    "gn:country":"LU",
    "gn:fcode":"PPL",
    "gn:population":0,
    "iso:country":"LU",
    "name:bul_x_preferred":[
        "\u0410\u0445\u043d"
    ],
    "name:cat_x_preferred":[
        "Ahn"
    ],
    "name:ceb_x_preferred":[
        "Ahn"
    ],
    "name:deu_x_preferred":[
        "Ahn"
    ],
    "name:eng_x_preferred":[
        "Ahn"
    ],
    "name:fra_x_preferred":[
        "Ahn"
    ],
    "name:lit_x_preferred":[
        "Onas"
    ],
    "name:ltz_x_preferred":[
        "On"
    ],
    "name:ltz_x_variant":[
        "Ohn"
    ],
    "name:msa_x_preferred":[
        "Ahn"
    ],
    "name:nld_x_preferred":[
        "Ahn"
    ],
    "name:pol_x_preferred":[
        "Ahn"
    ],
    "name:swe_x_preferred":[
        "Ahn"
    ],
    "qs_pg:aaroncc":"LU",
    "qs_pg:gn_country":"LU",
    "qs_pg:gn_fcode":"PPL",
    "qs_pg:gn_pop":0,
    "qs_pg:name":"Ahn",
    "qs_pg:name_adm0":"Luxembourg",
    "qs_pg:name_adm1":"Grevenmacher",
    "qs_pg:photos_9k":1,
    "qs_pg:photos_9r":1,
    "qs_pg:photos_all":1,
    "qs_pg:photos_sr":0,
    "qs_pg:pop_sr":0,
    "qs_pg:qs_pg_placetype":"locality",
    "qs_pg:qs_pg_placetype_gp":"Town",
    "qs_pg:woe_adm0":23424881,
    "woe:adm0_id":23424881,
    "woe:name_adm0":"Luxembourg",
    "woe:name_adm1":"Grevenmacher",
    "woe:placetype":"Town",
    "wof:lang_x_official":[
        "fra",
        "ltz",
        "deu"
    ],
    "wof:lang_x_spoken":[
        "fra",
        "ltz",
        "deu"
    ],
    "wof:name":"Ahn",
    "wof:placetype":"neighbourhood"
},
  "geometry": {"coordinates":[6.42167,49.62444],"type":"Point"}
}