{
  "type": "Feature",
  "properties": {
    "gn:admin1_code":"CL",
    "gn:admin2_code":"1.0",
    "gn:asciiname":"Lentzweiler",
    "gn:country_code":"LU",
    "gn:dem":520,
    "gn:feature_class":"P",
    "gn:feature_code":"PPLL",
    "gn:name":"Lentzweiler",
    "gn:population":0,
    "gn:timezone":"Europe/Luxembourg",
    "iso:country":"LU",
    "wof:name":"Lentzweiler",
    "wof:placetype":"locality"
},
  "geometry": {"coordinates":[5.98051,50.0667],"type":"Point"}
}