{
  "type": "Feature",
  "properties": {
    "iso:country":"LU",
    "name:als_x_preferred":[
        "Diddeleng"
    ],
    "name:ara_x_preferred":[
        "\u062f\u0648\u062f\u064a\u0644\u0627\u0646\u062c"
    ],
    "name:bel_x_preferred":[
        "\u0414\u0437\u044e\u0434\u0437\u0435\u043b\u0430\u043d\u0436"
    ],
    "name:cat_x_preferred":[
        "Dudelange"
    ],
    "name:ceb_x_preferred":[
        "Dudelange"
    ],
    "name:ces_x_preferred":[
        "Dudelange"
    ],
    "name:dan_x_preferred":[
        "Dudelange"
    ],
    "name:deu_x_preferred":[
        "D\u00fcdelingen"
    ],
    "name:diq_x_preferred":[
        "Dudelange"
    ],
    "name:eus_x_preferred":[
        "Dudelange"
    ],
    "name:fas_x_preferred":[
        "\u062f\u0648\u062f\u0644\u0627\u0646\u0698"
    ],
    "name:fra_x_preferred":[
        "Dudelange"
    ],
    "name:hun_x_preferred":[
        "Dudelange"
    ],
    "name:ita_x_preferred":[
        "Dudelange"
    ],
    "name:kat_x_preferred":[
        "\u10d3\u10d8\u10e3\u10d3\u10d4\u10da\u10d0\u10dc\u10df\u10d8"
    ],
    "name:kor_x_preferred":[
        "\ub4a4\ub4e4\ub791\uc8fc"
    ],
    "name:lit_x_preferred":[
        "Diudelan\u017eas"
    ],
    "name:ltz_x_preferred":[
        "Gemeng Diddeleng"
    ],
    "name:msa_x_preferred":[
        "Dudelange"
    ],
    "name:nld_x_preferred":[
        "Dudelange"
    ],
    "name:nno_x_preferred":[
        "Dudelange"
    ],
    "name:nor_x_preferred":[
        "Dudelange"
    ],
    "name:pol_x_preferred":[
        "Dudelange"
    ],
    "name:por_x_preferred":[
        "Dudelange"
    ],
    "name:ron_x_preferred":[
        "Dudelange"
    ],
    "name:rus_x_preferred":[
        "\u0414\u044e\u0434\u0435\u043b\u0430\u043d\u0436"
    ],
    "name:slk_x_preferred":[
        "Dudelange"
    ],
    "name:spa_x_preferred":[
        "Dudelange"
    ],
    "name:srp_x_preferred":[
        "\u0414\u0438\u0434\u0435\u043b\u0430\u043d\u0436"
    ],
    "name:swa_x_preferred":[
        "Dudelange"
    ],
    "name:swe_x_preferred":[
        "Dudelange"
    ],
    "name:tur_x_preferred":[
        "Dudelange"
    ],
    "name:ukr_x_preferred":[
        "\u0414\u044e\u0434\u0435\u043b\u0430\u043d\u0436"
    ],
    "name:vol_x_preferred":[
        "Dudelange"
    ],
    "qs_pg:aaroncc":"LU",
    "qs_pg:name":"Dudelange",
    "qs_pg:name_adm0":"Luxembourg",
    "qs_pg:name_adm1":"Luxembourg",
    "qs_pg:photos":55,
    "qs_pg:photos_1k":11,
    "qs_pg:photos_9k":3,
    "qs_pg:photos_9r":5,
    "qs_pg:photos_all":711,
    "qs_pg:photos_sr":2,
    "qs_pg:pop_sr":0,
    "qs_pg:qs_pg_placetype":"localadmin",
    "qs_pg:qs_pg_placetype_gp":"LocalAdmin",
    "qs_pg:woe_adm0":23424881,
    "woe:adm0_id":23424881,
    "woe:name_adm0":"Luxembourg",
    "woe:name_adm1":"Luxembourg",
    "woe:placetype":"LocalAdmin",
    "wof:name":"Dudelange",
    "wof:placetype":"localadmin"
},
  "geometry": {"coordinates":[6.0837,49.475932],"type":"Point"}
}