{
  "type": "Feature",
  "properties": {
    "gn:country":"LU",
    "gn:fcode":"PPL",
    "gn:population":380,
    "iso:country":"LU",
    "name:bel_x_preferred":[
        "\u0411\u0435\u0445"
    ],
    "name:bul_x_preferred":[
        "\u0411\u0435\u0445"
    ],
    "name:cat_x_preferred":[
        "Bech"
    ],
    "name:ceb_x_preferred":[
        "Bech"
    ],
    "name:dan_x_preferred":[
        "Bech"
    ],
    "name:deu_x_preferred":[
        "Bech"
    ],
    "name:eng_x_preferred":[
        "Bech"
    ],
    "name:fas_x_preferred":[
        "\u0628\u06a9"
    ],
    "name:fra_x_preferred":[
        "Bech"
    ],
    "name:gsw_x_preferred":[
        "Bech"
    ],
    "name:ita_x_preferred":[
        "Bech"
    ],
    "name:ltz_x_preferred":[
        "Gemeng Bech"
    ],
    "name:ltz_x_variant":[
        "Bech"
    ],
    "name:msa_x_preferred":[
        "Bech"
    ],
    "name:nan_x_preferred":[
        "Bech"
    ],
    "name:nld_x_preferred":[
        "Bech"
    ],
    "name:nob_x_preferred":[
        "Bech"
    ],
    "name:pol_x_preferred":[
        "Bech"
    ],
    "name:por_x_preferred":[
        "Bech"
    ],
    "name:rus_x_preferred":[
        "\u0411\u0435\u0445"
    ],
    "name:slk_x_preferred":[
        "Bech"
    ],
    "name:spa_x_preferred":[
        "Bech"
    ],
    "name:swe_x_preferred":[
        "Bech"
    ],
    "name:ukr_x_preferred":[
        "\u0411\u0435\u0445"
    ],
    "name:urd_x_preferred":[
        "\u0628\u06cc\u062e"
    ],
    "qs_pg:aaroncc":"LU",
    "qs_pg:gn_country":"LU",
    "qs_pg:gn_fcode":"PPL",
    "qs_pg:gn_pop":380,
    "qs_pg:name":"Bech",
    "qs_pg:name_adm0":"Luxembourg",
    "qs_pg:name_adm1":"Grevenmacher",
    "qs_pg:photos":60,
    "qs_pg:photos_1k":12,
    "qs_pg:photos_9k":1,
    "qs_pg:photos_9r":2,
    "qs_pg:photos_all":60,
    "qs_pg:photos_sr":2,
    "qs_pg:pop_sr":2,
    "qs_pg:qs_pg_placetype":"locality",
    "qs_pg:qs_pg_placetype_gp":"Town",
    "qs_pg:woe_adm0":23424881,
    "woe:adm0_id":23424881,
    "woe:name_adm0":"Luxembourg",
    "woe:name_adm1":"Grevenmacher",
    "woe:placetype":"Town",
    "wof:name":"Bech",
    "wof:placetype":"locality",
    "wof:population":380
},
  "geometry": {"coordinates":[6.36361,49.74611],"type":"Point"}
}