{
  "type": "Feature",
  "properties": {
    "gn:gn_country":"LU",
    "gn:gn_fcode":"PPL",
    "gn:gn_pop":396,
    "gn:population":396,
    "iso:country":"LU",
    "name:bel_x_preferred":[
        "\u0411\u0443\u043b\u0435\u0434"
    ],
    "name:bul_x_preferred":[
        "\u0411\u0443\u043b\u0435\u0434"
    ],
    "name:cat_x_preferred":[
        "Boulaide"
    ],
    "name:dan_x_preferred":[
        "Boulaide"
    ],
    "name:dut_x_preferred":[
        "Boulaide"
    ],
    "name:eng_x_preferred":[
        "Boulaide"
    ],
    "name:fre_x_preferred":[
        "Boulaide"
    ],
    "name:ger_x_preferred":[
        "Bauschleiden"
    ],
    "name:gsw_x_preferred":[
        "Bauschelt"
    ],
    "name:ita_x_preferred":[
        "Boulaide"
    ],
    "name:jpn_x_preferred":[
        "\u30d0\u30c3\u30b7\u30e5\u30eb\u30a4\u30fc\u30c9\u30f3"
    ],
    "name:ltz_x_preferred":[
        "Gemeng Bauschelt"
    ],
    "name:may_x_preferred":[
        "Boulaide"
    ],
    "name:nan_x_preferred":[
        "Boulaide"
    ],
    "name:nob_x_preferred":[
        "Boulaide"
    ],
    "name:per_x_preferred":[
        "\u0628\u0648\u0644\u062f\u060c \u0644\u0648\u06a9\u0632\u0627\u0645\u0628\u0648\u0631\u06af"
    ],
    "name:pol_x_preferred":[
        "Boulaide"
    ],
    "name:por_x_preferred":[
        "Boulaide"
    ],
    "name:rus_x_preferred":[
        "\u0411\u0443\u043b\u0435\u0434"
    ],
    "name:slo_x_preferred":[
        "Boulaide"
    ],
    "name:swe_x_preferred":[
        "Boulaide"
    ],
    "name:ukr_x_preferred":[
        "\u0411\u0443\u043b\u0435\u0434"
    ],
    "name:unk_x_variant":[
        "Bauschleiden"
    ],
    "qs_pg:aaroncc":"LU",
    "qs_pg:gn_country":"LU",
    "qs_pg:gn_fcode":"PPL",
    "qs_pg:gn_pop":396,
    "qs_pg:name":"Boulaide",
    "qs_pg:name_adm0":"Luxembourg",
    "qs_pg:name_adm1":"Diekirch",
    "qs_pg:photos":167,
    "qs_pg:photos_1k":34,
    "qs_pg:photos_9k":1,
    "qs_pg:photos_9r":4,
    "qs_pg:photos_all":167,
    "qs_pg:photos_sr":4,
    "qs_pg:pop_sr":2,
    "qs_pg:qs_pg_placetype":"locality",
    "qs_pg:qs_pg_placetype_gp":"Town",
    "qs_pg:woe_adm0":23424881,
    "woe:adm0_id":23424881,
    "woe:name_adm0":"Luxembourg",
    "woe:name_adm1":"Diekirch",
    "woe:placetype":"Town",
    "wof:name":"Boulaide",
    "wof:placetype":"locality",
    "wof:population":396
},
  "geometry": {"coordinates":[5.81639,49.88778],"type":"Point"}
}