{
  "type": "Feature",
  "properties": {
    "gn:gn_country":"LU",
    "gn:gn_fcode":"PPLX",
    "gn:gn_pop":0,
    "iso:country":"LU",
    "name:cat_x_preferred":[
        "Eich"
    ],
    "name:dut_x_preferred":[
        "Eich"
    ],
    "name:eng_x_preferred":[
        "Eich"
    ],
    "name:fre_x_preferred":[
        "Eich"
    ],
    "name:ita_x_preferred":[
        "Eich"
    ],
    "name:ltz_x_preferred":[
        "Eech"
    ],
    "name:swe_x_preferred":[
        "Eich"
    ],
    "qs_pg:aaroncc":"LU",
    "qs_pg:gn_country":"LU",
    "qs_pg:gn_fcode":"PPLX",
    "qs_pg:gn_pop":0,
    "qs_pg:name":"Eich",
    "qs_pg:name_adm0":"Luxembourg",
    "qs_pg:name_adm1":"Luxembourg",
    "qs_pg:photos":196,
    "qs_pg:photos_1k":40,
    "qs_pg:photos_9k":1,
    "qs_pg:photos_9r":4,
    "qs_pg:photos_all":196,
    "qs_pg:photos_sr":4,
    "qs_pg:pop_sr":0,
    "qs_pg:qs_pg_placetype":"neighbourhood",
    "qs_pg:qs_pg_placetype_gp":"Suburb",
    "qs_pg:woe_adm0":23424881,
    "woe:adm0_id":23424881,
    "woe:name_adm0":"Luxembourg",
    "woe:name_adm1":"Luxembourg",
    "woe:placetype":"Suburb",
    "wof:name":"Eich",
    "wof:placetype":"neighbourhood"
},
  "geometry": {"coordinates":[6.13194,49.62889],"type":"Point"}
}