{
  "type": "Feature",
  "properties": {
    "gn:country":"LU",
    "gn:fcode":"PPL",
    "gn:population":65,
    "iso:country":"LU",
    "name:bel_x_preferred":[
        "\u041d\u043e\u0439\u043d\u0445\u0430\u045e\u0437\u0435\u043d"
    ],
    "name:cat_x_preferred":[
        "Neunhausen"
    ],
    "name:ceb_x_preferred":[
        "Neunhausen"
    ],
    "name:dan_x_preferred":[
        "Neunhausen"
    ],
    "name:deu_x_preferred":[
        "Neunhausen"
    ],
    "name:eng_x_preferred":[
        "Neunhausen"
    ],
    "name:fra_x_preferred":[
        "Neunhausen"
    ],
    "name:gsw_x_preferred":[
        "N\u00e9ngsen"
    ],
    "name:ita_x_preferred":[
        "Neunhausen"
    ],
    "name:ltz_x_preferred":[
        "Gemeng N\u00e9ngsen"
    ],
    "name:msa_x_preferred":[
        "Neunhausen"
    ],
    "name:nan_x_preferred":[
        "Neunhausen"
    ],
    "name:nld_x_preferred":[
        "Neunhausen"
    ],
    "name:nob_x_preferred":[
        "Neunhausen"
    ],
    "name:pol_x_preferred":[
        "Neunhausen"
    ],
    "name:por_x_preferred":[
        "Neunhausen"
    ],
    "name:rus_x_preferred":[
        "\u041d\u043e\u0439\u043d\u0445\u0430\u0443\u0437\u0435\u043d"
    ],
    "name:slk_x_preferred":[
        "Neunhausen"
    ],
    "name:spa_x_preferred":[
        "Neunhausen"
    ],
    "name:swe_x_preferred":[
        "Neunhausen"
    ],
    "name:ukr_x_preferred":[
        "\u041d\u043e\u0439\u043d\u0433\u0430\u0443\u0437\u0435\u043d"
    ],
    "qs_pg:aaroncc":"LU",
    "qs_pg:gn_country":"LU",
    "qs_pg:gn_fcode":"PPL",
    "qs_pg:gn_pop":65,
    "qs_pg:name":"Neunhausen",
    "qs_pg:name_adm0":"Luxembourg",
    "qs_pg:name_adm1":"Diekirch",
    "qs_pg:photos":27,
    "qs_pg:photos_1k":5,
    "qs_pg:photos_9k":1,
    "qs_pg:photos_9r":2,
    "qs_pg:photos_all":27,
    "qs_pg:photos_sr":2,
    "qs_pg:pop_sr":1,
    "qs_pg:qs_pg_placetype":"locality",
    "qs_pg:qs_pg_placetype_gp":"Town",
    "qs_pg:woe_adm0":23424881,
    "woe:adm0_id":23424881,
    "woe:name_adm0":"Luxembourg",
    "woe:name_adm1":"Diekirch",
    "woe:placetype":"Town",
    "wof:lang_x_official":[
        "fra",
        "ltz",
        "deu"
    ],
    "wof:lang_x_spoken":[
        "fra",
        "ltz",
        "deu"
    ],
    "wof:name":"Neunhausen",
    "wof:placetype":"neighbourhood",
    "wof:population":65
},
  "geometry": {"coordinates":[5.88722,49.8775],"type":"Point"}
}