{
  "type": "Feature",
  "properties": {
    "gn:admin1_code":"RD",
    "gn:admin2_code":"6.0",
    "gn:asciiname":"Martelinville",
    "gn:cc2":"LU",
    "gn:country_code":"LU",
    "gn:dem":353,
    "gn:feature_class":"P",
    "gn:feature_code":"PPLL",
    "gn:name":"Martelinville",
    "gn:population":0,
    "gn:timezone":"Europe/Luxembourg",
    "iso:country":"LU",
    "name:und_x_variant":[
        "Rommelerhof",
        "Ferme Martelinville",
        "Rommeldange",
        "Rommelerhaff",
        "Martelinville"
    ],
    "wof:name":"Martelinville",
    "wof:placetype":"locality"
},
  "geometry": {"coordinates":[5.77333,49.86694],"type":"Point"}
}