{
  "type": "Feature",
  "properties": {
    "gn:gn_country":"LU",
    "gn:gn_fcode":"ADM3",
    "gn:gn_pop":0,
    "iso:country":"LU",
    "name:als_x_preferred":[
        "K\u00e4erch"
    ],
    "name:bel_x_preferred":[
        "\u041a\u0451\u0440\u044b\u0445"
    ],
    "name:cat_x_preferred":[
        "Koerich"
    ],
    "name:ceb_x_preferred":[
        "Koerich"
    ],
    "name:dan_x_preferred":[
        "Koerich"
    ],
    "name:deu_x_preferred":[
        "Koerich"
    ],
    "name:fas_x_preferred":[
        "\u06a9\u0648\u0626\u0631\u06cc\u0634"
    ],
    "name:fra_x_preferred":[
        "Koerich"
    ],
    "name:ita_x_preferred":[
        "Koerich"
    ],
    "name:ltz_x_preferred":[
        "Gemeng K\u00e4erch"
    ],
    "name:msa_x_preferred":[
        "Koerich"
    ],
    "name:nds_x_preferred":[
        "Gemeen Koerich"
    ],
    "name:nld_x_preferred":[
        "Koerich"
    ],
    "name:nor_x_preferred":[
        "Koerich"
    ],
    "name:pol_x_preferred":[
        "Koerich"
    ],
    "name:por_x_preferred":[
        "Koerich"
    ],
    "name:rus_x_preferred":[
        "\u041a\u0451\u0440\u0438\u0445"
    ],
    "name:slk_x_preferred":[
        "Koerich"
    ],
    "name:swe_x_preferred":[
        "Koerich"
    ],
    "name:ukr_x_preferred":[
        "\u041a\u0435\u0440\u0456\u0445"
    ],
    "qs_pg:aaroncc":"LU",
    "qs_pg:gn_country":"LU",
    "qs_pg:gn_fcode":"ADM3",
    "qs_pg:gn_pop":0,
    "qs_pg:name":"Koerich",
    "qs_pg:name_adm0":"Luxembourg",
    "qs_pg:name_adm1":"Luxembourg",
    "qs_pg:photos":184,
    "qs_pg:photos_1k":37,
    "qs_pg:photos_9k":2,
    "qs_pg:photos_9r":5,
    "qs_pg:photos_all":363,
    "qs_pg:photos_sr":4,
    "qs_pg:pop_sr":0,
    "qs_pg:qs_pg_placetype":"localadmin",
    "qs_pg:qs_pg_placetype_gp":"LocalAdmin",
    "qs_pg:woe_adm0":23424881,
    "woe:adm0_id":23424881,
    "woe:name_adm0":"Luxembourg",
    "woe:name_adm1":"Luxembourg",
    "woe:placetype":"LocalAdmin",
    "wof:name":"Koerich",
    "wof:placetype":"localadmin"
},
  "geometry": {"coordinates":[5.95,49.67],"type":"Point"}
}