{
  "type": "Feature",
  "properties": {
    "gn:country":"LU",
    "gn:fcode":"PPL",
    "gn:population":605,
    "iso:country":"LU",
    "name:bel_x_preferred":[
        "\u0422\u0443\u043d\u0442\u0430\u043d\u0436"
    ],
    "name:bul_x_preferred":[
        "\u0422\u0443\u043d\u0442\u0430\u043d\u0436"
    ],
    "name:cat_x_preferred":[
        "Tuntange"
    ],
    "name:ceb_x_preferred":[
        "Tuntange"
    ],
    "name:dan_x_preferred":[
        "Tuntange"
    ],
    "name:deu_x_preferred":[
        "Tuntange"
    ],
    "name:deu_x_variant":[
        "T\u00fcntingen"
    ],
    "name:eng_x_preferred":[
        "Tuntange"
    ],
    "name:fas_x_preferred":[
        "\u062a\u0648\u0646\u062a\u0627\u0646\u0698"
    ],
    "name:fra_x_preferred":[
        "Tuntange"
    ],
    "name:gsw_x_preferred":[
        "T\u00ebnten"
    ],
    "name:ita_x_preferred":[
        "Tuntange"
    ],
    "name:ltz_x_preferred":[
        "T\u00ebnten"
    ],
    "name:msa_x_preferred":[
        "Tuntange"
    ],
    "name:nan_x_preferred":[
        "Tuntange"
    ],
    "name:nld_x_preferred":[
        "Tuntange"
    ],
    "name:nob_x_preferred":[
        "Tuntange"
    ],
    "name:pol_x_preferred":[
        "Tuntange"
    ],
    "name:por_x_preferred":[
        "Tuntange"
    ],
    "name:pus_x_preferred":[
        "\u067c\u0648\u0646\u067c\u0627\u0646\u06ab"
    ],
    "name:rus_x_preferred":[
        "\u0422\u0443\u043d\u0442\u0430\u043d\u0436"
    ],
    "name:slk_x_preferred":[
        "Tuntange"
    ],
    "name:swe_x_preferred":[
        "Tuntange"
    ],
    "name:tur_x_preferred":[
        "Tuntange"
    ],
    "name:ukr_x_preferred":[
        "\u0422\u0443\u043d\u0442\u0430\u043d\u0436"
    ],
    "name:und_x_variant":[
        "Tuntingen"
    ],
    "name:zho_x_preferred":[
        "\u5766\u5510\u65e5"
    ],
    "qs_pg:aaroncc":"LU",
    "qs_pg:gn_country":"LU",
    "qs_pg:gn_fcode":"PPL",
    "qs_pg:gn_pop":605,
    "qs_pg:name":"Tuntange",
    "qs_pg:name_adm0":"Luxembourg",
    "qs_pg:name_adm1":"Luxembourg",
    "qs_pg:photos_9k":1,
    "qs_pg:photos_9r":1,
    "qs_pg:photos_all":4,
    "qs_pg:photos_sr":0,
    "qs_pg:pop_sr":2,
    "qs_pg:qs_pg_placetype":"locality",
    "qs_pg:qs_pg_placetype_gp":"Town",
    "qs_pg:woe_adm0":23424881,
    "woe:adm0_id":23424881,
    "woe:name_adm0":"Luxembourg",
    "woe:name_adm1":"Luxembourg",
    "woe:placetype":"Town",
    "wof:lang_x_official":[
        "fra",
        "ltz",
        "deu"
    ],
    "wof:lang_x_spoken":[
        "fra",
        "ltz",
        "deu"
    ],
    "wof:name":"Tuntange",
    "wof:placetype":"neighbourhood",
    "wof:population":605
},
  "geometry": {"coordinates":[6.01028,49.71778],"type":"Point"}
}