{
  "type": "Feature",
  "properties": {
    "iso:country":"LU",
    "name:cat_x_preferred":[
        "Bettborn"
    ],
    "name:ceb_x_preferred":[
        "Bettborn"
    ],
    "name:fra_x_preferred":[
        "Bettborn"
    ],
    "name:ltz_x_preferred":[
        "Bieberech"
    ],
    "name:msa_x_preferred":[
        "Bettborn"
    ],
    "name:pol_x_preferred":[
        "Bettborn"
    ],
    "name:swe_x_preferred":[
        "Bettborn"
    ],
    "name:zho_x_preferred":[
        "\u8d1d\u7279\u535a\u5c14\u6069"
    ],
    "qs_pg:aaroncc":"LU",
    "qs_pg:name":"Bettborn",
    "qs_pg:name_adm0":"Luxembourg",
    "qs_pg:name_adm1":"Diekirch",
    "qs_pg:photos":190,
    "qs_pg:photos_1k":39,
    "qs_pg:photos_9k":1,
    "qs_pg:photos_9r":4,
    "qs_pg:photos_all":239,
    "qs_pg:photos_sr":4,
    "qs_pg:pop_sr":0,
    "qs_pg:qs_pg_placetype":"localadmin",
    "qs_pg:qs_pg_placetype_gp":"LocalAdmin",
    "qs_pg:woe_adm0":23424881,
    "woe:adm0_id":23424881,
    "woe:name_adm0":"Luxembourg",
    "woe:name_adm1":"Diekirch",
    "woe:placetype":"LocalAdmin",
    "wof:name":"Bettborn",
    "wof:placetype":"localadmin"
},
  "geometry": {"coordinates":[5.920214,49.798565],"type":"Point"}
}