{
  "type": "Feature",
  "properties": {
    "gn:admin1_code":"EC",
    "gn:admin2_code":"2.0",
    "gn:asciiname":"Wolpert",
    "gn:cc2":"LU",
    "gn:country_code":"LU",
    "gn:dem":370,
    "gn:feature_class":"P",
    "gn:feature_code":"PPLL",
    "gn:name":"Wolpert",
    "gn:population":0,
    "gn:timezone":"Europe/Luxembourg",
    "iso:country":"LU",
    "name:und_x_variant":[
        "Wolper",
        "Maisons Wolper",
        "Wolpert"
    ],
    "wof:name":"Wolpert",
    "wof:placetype":"neighbourhood"
},
  "geometry": {"coordinates":[6.3536,49.76421],"type":"Point"}
}