{
  "type": "Feature",
  "properties": {
    "gn:admin1_code":"CL",
    "gn:admin2_code":"1.0",
    "gn:asciiname":"Troine",
    "gn:cc2":"LU",
    "gn:country_code":"LU",
    "gn:dem":476,
    "gn:feature_class":"P",
    "gn:feature_code":"PPL",
    "gn:name":"Troine",
    "gn:population":0,
    "gn:timezone":"Europe/Luxembourg",
    "iso:country":"LU",
    "name:cat_x_preferred":[
        "Troine"
    ],
    "name:ceb_x_preferred":[
        "Troine"
    ],
    "name:deu_x_preferred":[
        "Trotten"
    ],
    "name:fra_x_preferred":[
        "Troine"
    ],
    "name:ltz_x_preferred":[
        "Tratten"
    ],
    "name:msa_x_preferred":[
        "Troine"
    ],
    "name:pol_x_preferred":[
        "Troine"
    ],
    "name:swe_x_preferred":[
        "Troine"
    ],
    "wof:lang_x_official":[
        "fra",
        "ltz",
        "deu"
    ],
    "wof:lang_x_spoken":[
        "fra",
        "ltz",
        "deu"
    ],
    "wof:name":"Troine",
    "wof:placetype":"neighbourhood"
},
  "geometry": {"coordinates":[5.88306,50.06444],"type":"Point"}
}