{
  "type": "Feature",
  "properties": {
    "gn:country":"LU",
    "gn:fcode":"PPL",
    "gn:population":781,
    "iso:country":"LU",
    "name:cat_x_preferred":[
        "Oetrange"
    ],
    "name:ceb_x_preferred":[
        "Oetrange"
    ],
    "name:deu_x_preferred":[
        "Oetringen"
    ],
    "name:eng_x_preferred":[
        "Oetrange"
    ],
    "name:epo_x_preferred":[
        "Oetrange"
    ],
    "name:fra_x_preferred":[
        "Oetrange"
    ],
    "name:hun_x_preferred":[
        "Oetrange"
    ],
    "name:ltz_x_preferred":[
        "\u00c9iter"
    ],
    "name:nld_x_preferred":[
        "Oetrange"
    ],
    "name:nob_x_preferred":[
        "Oetrange"
    ],
    "name:pol_x_preferred":[
        "Oetrange"
    ],
    "name:swe_x_preferred":[
        "Oetrange"
    ],
    "qs_pg:aaroncc":"LU",
    "qs_pg:gn_country":"LU",
    "qs_pg:gn_fcode":"PPL",
    "qs_pg:gn_pop":781,
    "qs_pg:name":"Oetrange",
    "qs_pg:name_adm0":"Luxembourg",
    "qs_pg:name_adm1":"Luxembourg",
    "qs_pg:photos":40,
    "qs_pg:photos_1k":8,
    "qs_pg:photos_9k":1,
    "qs_pg:photos_9r":2,
    "qs_pg:photos_all":40,
    "qs_pg:photos_sr":2,
    "qs_pg:pop_sr":2,
    "qs_pg:qs_pg_placetype":"locality",
    "qs_pg:qs_pg_placetype_gp":"Town",
    "qs_pg:woe_adm0":23424881,
    "woe:adm0_id":23424881,
    "woe:name_adm0":"Luxembourg",
    "woe:name_adm1":"Luxembourg",
    "woe:placetype":"Town",
    "wof:lang_x_official":[
        "fra",
        "ltz",
        "deu"
    ],
    "wof:lang_x_spoken":[
        "fra",
        "ltz",
        "deu"
    ],
    "wof:name":"Oetrange",
    "wof:placetype":"neighbourhood",
    "wof:population":781
},
  "geometry": {"coordinates":[6.26,49.59639],"type":"Point"}
}