{
  "type": "Feature",
  "properties": {
    "gn:country":"LU",
    "gn:fcode":"PPL",
    "gn:population":465,
    "iso:country":"LU",
    "name:ast_x_preferred":[
        "Blaschette"
    ],
    "name:cat_x_preferred":[
        "Blaschette"
    ],
    "name:ceb_x_preferred":[
        "Blaschette"
    ],
    "name:eng_x_preferred":[
        "Blaschette"
    ],
    "name:fra_x_preferred":[
        "Blaschette"
    ],
    "name:ltz_x_preferred":[
        "Blaaschent"
    ],
    "name:nld_x_preferred":[
        "Blaschette"
    ],
    "name:pol_x_preferred":[
        "Blaschette"
    ],
    "name:swe_x_preferred":[
        "Blaschette"
    ],
    "qs_pg:aaroncc":"LU",
    "qs_pg:gn_country":"LU",
    "qs_pg:gn_fcode":"PPL",
    "qs_pg:gn_pop":465,
    "qs_pg:name":"Blaschette",
    "qs_pg:name_adm0":"Luxembourg",
    "qs_pg:name_adm1":"Luxembourg",
    "qs_pg:photos_9k":1,
    "qs_pg:photos_9r":1,
    "qs_pg:photos_all":19,
    "qs_pg:photos_sr":0,
    "qs_pg:pop_sr":2,
    "qs_pg:qs_pg_placetype":"locality",
    "qs_pg:qs_pg_placetype_gp":"Town",
    "qs_pg:woe_adm0":23424881,
    "woe:adm0_id":23424881,
    "woe:name_adm0":"Luxembourg",
    "woe:name_adm1":"Luxembourg",
    "woe:placetype":"Town",
    "wof:lang_x_official":[
        "fra",
        "ltz",
        "deu"
    ],
    "wof:lang_x_spoken":[
        "fra",
        "ltz",
        "deu"
    ],
    "wof:name":"Blaschette",
    "wof:placetype":"neighbourhood",
    "wof:population":465
},
  "geometry": {"coordinates":[6.17056,49.69722],"type":"Point"}
}