{
  "type": "Feature",
  "properties": {
    "gn:admin1_code":"RM",
    "gn:admin2_code":"2.0",
    "gn:asciiname":"Wolfsmuhle-les-Ellange",
    "gn:country_code":"LU",
    "gn:dem":178,
    "gn:feature_class":"P",
    "gn:feature_code":"PPL",
    "gn:name":"Wolfsmuhle-l\u00e8s-Ellange",
    "gn:population":0,
    "gn:timezone":"Europe/Luxembourg",
    "iso:country":"LU",
    "name:und_x_variant":[
        "Wolfsm\u00fchle",
        "Wolfsmuhle-l\u00e8s-Ellange"
    ],
    "wof:lang_x_official":[
        "fra",
        "ltz",
        "deu"
    ],
    "wof:lang_x_spoken":[
        "fra",
        "ltz",
        "deu"
    ],
    "wof:name":"Wolfsmuhle-les-Ellange",
    "wof:placetype":"neighbourhood"
},
  "geometry": {"coordinates":[6.31667,49.53333],"type":"Point"}
}