{
  "type": "Feature",
  "properties": {
    "gn:country":"LU",
    "gn:fcode":"PPL",
    "gn:population":358,
    "iso:country":"LU",
    "name:cat_x_preferred":[
        "Wolwelange"
    ],
    "name:ceb_x_preferred":[
        "Wolwelange"
    ],
    "name:deu_x_preferred":[
        "Wolwelingen"
    ],
    "name:eng_x_preferred":[
        "Wolwelange"
    ],
    "name:fra_x_preferred":[
        "Wolwelange"
    ],
    "name:ltz_x_preferred":[
        "Wolwen"
    ],
    "name:nld_x_preferred":[
        "Wolwelange"
    ],
    "name:pol_x_preferred":[
        "Wolwelange"
    ],
    "name:swe_x_preferred":[
        "Wolwelange"
    ],
    "qs_pg:aaroncc":"LU",
    "qs_pg:gn_country":"LU",
    "qs_pg:gn_fcode":"PPL",
    "qs_pg:gn_pop":358,
    "qs_pg:name":"Wolwelange",
    "qs_pg:photos_9r":0,
    "qs_pg:photos_sr":0,
    "qs_pg:pop_sr":2,
    "qs_pg:qs_pg_placetype":"locality",
    "wof:lang_x_official":[
        "fra",
        "ltz",
        "deu"
    ],
    "wof:lang_x_spoken":[
        "fra",
        "ltz",
        "deu"
    ],
    "wof:name":"Wolwelange",
    "wof:placetype":"neighbourhood",
    "wof:population":358
},
  "geometry": {"coordinates":[5.76472,49.82861],"type":"Point"}
}