{
  "type": "Feature",
  "properties": {
    "gn:gn_country":"LU",
    "gn:gn_fcode":"PPL",
    "gn:gn_pop":67,
    "gn:population":67,
    "iso:country":"LU",
    "name:cat_x_preferred":[
        "Bour"
    ],
    "name:dut_x_preferred":[
        "Bour"
    ],
    "name:eng_x_preferred":[
        "Bour"
    ],
    "name:fre_x_preferred":[
        "Bour"
    ],
    "name:ltz_x_preferred":[
        "Bur"
    ],
    "qs_pg:aaroncc":"LU",
    "qs_pg:gn_country":"LU",
    "qs_pg:gn_fcode":"PPL",
    "qs_pg:gn_pop":67,
    "qs_pg:name":"Bour",
    "qs_pg:name_adm0":"Luxembourg",
    "qs_pg:name_adm1":"Luxembourg",
    "qs_pg:photos_9k":1,
    "qs_pg:photos_9r":1,
    "qs_pg:photos_all":1,
    "qs_pg:photos_sr":0,
    "qs_pg:pop_sr":1,
    "qs_pg:qs_pg_placetype":"locality",
    "qs_pg:qs_pg_placetype_gp":"Town",
    "qs_pg:woe_adm0":23424881,
    "woe:adm0_id":23424881,
    "woe:name_adm0":"Luxembourg",
    "woe:name_adm1":"Luxembourg",
    "woe:placetype":"Town",
    "wof:name":"Bour",
    "wof:placetype":"locality",
    "wof:population":67
},
  "geometry": {"coordinates":[6.01889,49.70139],"type":"Point"}
}