{
  "type": "Feature",
  "properties": {
    "gn:country":"LU",
    "gn:fcode":"ADM3",
    "gn:population":0,
    "iso:country":"LU",
    "name:als_x_preferred":[
        "Wahl"
    ],
    "name:ceb_x_preferred":[
        "Wahl"
    ],
    "name:ces_x_preferred":[
        "Wahl"
    ],
    "name:deu_x_preferred":[
        "Wahl"
    ],
    "name:fin_x_preferred":[
        "Wahl"
    ],
    "name:fra_x_preferred":[
        "Wahl"
    ],
    "name:hun_x_preferred":[
        "Wahl"
    ],
    "name:hye_x_preferred":[
        "\u054e\u0561\u056c"
    ],
    "name:ita_x_preferred":[
        "Wahl"
    ],
    "name:nld_x_preferred":[
        "Wahl"
    ],
    "name:pol_x_preferred":[
        "Wahl"
    ],
    "name:rus_x_preferred":[
        "\u0412\u0430\u043b\u044c"
    ],
    "name:swe_x_preferred":[
        "Wahl"
    ],
    "qs_pg:aaroncc":"LU",
    "qs_pg:gn_country":"LU",
    "qs_pg:gn_fcode":"ADM3",
    "qs_pg:gn_pop":0,
    "qs_pg:name":"Wahl",
    "qs_pg:name_adm0":"Luxembourg",
    "qs_pg:name_adm1":"Diekirch",
    "qs_pg:photos":1,
    "qs_pg:photos_1k":1,
    "qs_pg:photos_9k":1,
    "qs_pg:photos_9r":2,
    "qs_pg:photos_all":49,
    "qs_pg:photos_sr":1,
    "qs_pg:pop_sr":0,
    "qs_pg:qs_pg_placetype":"localadmin",
    "qs_pg:qs_pg_placetype_gp":"LocalAdmin",
    "qs_pg:woe_adm0":23424881,
    "woe:adm0_id":23424881,
    "woe:name_adm0":"Luxembourg",
    "woe:name_adm1":"Diekirch",
    "woe:placetype":"LocalAdmin",
    "wof:name":"Wahl",
    "wof:placetype":"localadmin"
},
  "geometry": {"coordinates":[5.90639,49.83667],"type":"Point"}
}