{
  "type": "Feature",
  "properties": {
    "gn:country":"LU",
    "gn:fcode":"ADM3",
    "gn:population":0,
    "iso:country":"LU",
    "name:als_x_preferred":[
        "Ierpeldeng"
    ],
    "name:bel_x_preferred":[
        "\u042d\u0440\u043f\u0435\u043b\u044c\u0434\u0430\u043d\u0436"
    ],
    "name:cat_x_preferred":[
        "Erpeldange"
    ],
    "name:ceb_x_preferred":[
        "Erpeldange"
    ],
    "name:dan_x_preferred":[
        "Erpeldange"
    ],
    "name:fas_x_preferred":[
        "\u0627\u0631\u067e\u0644\u062f\u0627\u0646\u0698"
    ],
    "name:fra_x_preferred":[
        "Erpeldange-sur-S\u00fbre"
    ],
    "name:ita_x_preferred":[
        "Erpeldange"
    ],
    "name:kor_x_preferred":[
        "\uc5d0\ub974\ud3a0\ub2f9\uc8fc"
    ],
    "name:lim_x_preferred":[
        "Erpeldange"
    ],
    "name:msa_x_preferred":[
        "Erpeldange"
    ],
    "name:nld_x_preferred":[
        "Erpeldange-sur-S\u00fbre"
    ],
    "name:nor_x_preferred":[
        "Erpeldange"
    ],
    "name:pol_x_preferred":[
        "Erpeldange"
    ],
    "name:por_x_preferred":[
        "Erpeldange"
    ],
    "name:rus_x_preferred":[
        "\u042d\u0440\u043f\u0435\u043b\u044c\u0434\u0430\u043d\u0436"
    ],
    "name:slk_x_preferred":[
        "Erpeldange"
    ],
    "name:swe_x_preferred":[
        "Erpeldange"
    ],
    "name:ukr_x_preferred":[
        "\u0415\u0440\u043f\u0435\u043b\u044c\u0434\u0430\u043d\u0436"
    ],
    "qs_pg:aaroncc":"LU",
    "qs_pg:gn_country":"LU",
    "qs_pg:gn_fcode":"ADM3",
    "qs_pg:gn_pop":0,
    "qs_pg:name":"Erpeldange",
    "qs_pg:name_adm0":"Luxembourg",
    "qs_pg:name_adm1":"Diekirch",
    "qs_pg:photos":1,
    "qs_pg:photos_1k":1,
    "qs_pg:photos_9k":1,
    "qs_pg:photos_9r":2,
    "qs_pg:photos_all":58,
    "qs_pg:photos_sr":1,
    "qs_pg:pop_sr":0,
    "qs_pg:qs_pg_placetype":"localadmin",
    "qs_pg:qs_pg_placetype_gp":"LocalAdmin",
    "qs_pg:woe_adm0":23424881,
    "woe:adm0_id":23424881,
    "woe:name_adm0":"Luxembourg",
    "woe:name_adm1":"Diekirch",
    "woe:placetype":"LocalAdmin",
    "wof:name":"Erpeldange",
    "wof:placetype":"localadmin"
},
  "geometry": {"coordinates":[6.11472,49.86472],"type":"Point"}
}