{
  "type": "Feature",
  "properties": {
    "gn:country":"LU",
    "gn:fcode":"PPL",
    "gn:population":293,
    "iso:country":"LU",
    "name:cat_x_preferred":[
        "Fennange"
    ],
    "name:ceb_x_preferred":[
        "Fennange"
    ],
    "name:deu_x_preferred":[
        "Fenningen"
    ],
    "name:eng_x_preferred":[
        "Fennange"
    ],
    "name:fra_x_preferred":[
        "Fennange"
    ],
    "name:ltz_x_preferred":[
        "Fenneng"
    ],
    "name:nld_x_preferred":[
        "Fennange"
    ],
    "name:pol_x_preferred":[
        "Fennange"
    ],
    "name:spa_x_preferred":[
        "Fennange"
    ],
    "name:swe_x_preferred":[
        "Fennange"
    ],
    "qs_pg:aaroncc":"LU",
    "qs_pg:gn_country":"LU",
    "qs_pg:gn_fcode":"PPL",
    "qs_pg:gn_pop":293,
    "qs_pg:name":"Fennange",
    "qs_pg:name_adm0":"Luxembourg",
    "qs_pg:name_adm1":"Luxembourg",
    "qs_pg:photos_9k":1,
    "qs_pg:photos_9r":1,
    "qs_pg:photos_all":3,
    "qs_pg:photos_sr":0,
    "qs_pg:pop_sr":2,
    "qs_pg:qs_pg_placetype":"locality",
    "qs_pg:qs_pg_placetype_gp":"Town",
    "qs_pg:woe_adm0":23424881,
    "woe:adm0_id":23424881,
    "woe:name_adm0":"Luxembourg",
    "woe:name_adm1":"Luxembourg",
    "woe:placetype":"Town",
    "wof:lang_x_official":[
        "fra",
        "ltz",
        "deu"
    ],
    "wof:lang_x_spoken":[
        "fra",
        "ltz",
        "deu"
    ],
    "wof:name":"Fennange",
    "wof:placetype":"neighbourhood",
    "wof:population":293
},
  "geometry": {"coordinates":[6.07833,49.51972],"type":"Point"}
}