{
  "type": "Feature",
  "properties": {
    "gn:country":"LU",
    "gn:fcode":"PPL",
    "gn:population":191,
    "iso:country":"LU",
    "name:bel_x_preferred":[
        "\u0411\u0443\u0440\u043c\u0435\u0440\u0430\u043d\u0436"
    ],
    "name:cat_x_preferred":[
        "Burmerange"
    ],
    "name:ceb_x_preferred":[
        "Burmerange"
    ],
    "name:dan_x_preferred":[
        "Burmerange"
    ],
    "name:deu_x_preferred":[
        "B\u00fcrmeringen"
    ],
    "name:eng_x_preferred":[
        "Burmerange"
    ],
    "name:fra_x_preferred":[
        "Burmerange"
    ],
    "name:gsw_x_preferred":[
        "Biermereng"
    ],
    "name:ita_x_preferred":[
        "Burmerange"
    ],
    "name:ltz_x_preferred":[
        "Gemeng Biermereng"
    ],
    "name:msa_x_preferred":[
        "Burmerange"
    ],
    "name:nan_x_preferred":[
        "Burmerange"
    ],
    "name:nld_x_preferred":[
        "Burmerange"
    ],
    "name:nob_x_preferred":[
        "Burmerange"
    ],
    "name:pol_x_preferred":[
        "Burmerange"
    ],
    "name:por_x_preferred":[
        "Burmerange"
    ],
    "name:rus_x_preferred":[
        "\u0411\u0443\u0440\u043c\u0435\u0440\u0430\u043d\u0436"
    ],
    "name:slk_x_preferred":[
        "Burmerange"
    ],
    "name:swe_x_preferred":[
        "Burmerange"
    ],
    "name:ukr_x_preferred":[
        "\u0411\u0443\u0440\u043c\u0435\u0440\u0430\u043d\u0436"
    ],
    "name:zho_x_preferred":[
        "\u6bd4\u5c14\u9ed8\u6717\u65e5"
    ],
    "qs_pg:aaroncc":"LU",
    "qs_pg:gn_country":"LU",
    "qs_pg:gn_fcode":"PPL",
    "qs_pg:gn_pop":191,
    "qs_pg:name":"Burmerange",
    "qs_pg:name_adm0":"Luxembourg",
    "qs_pg:name_adm1":"Grevenmacher",
    "qs_pg:photos_9k":1,
    "qs_pg:photos_9r":1,
    "qs_pg:photos_all":3,
    "qs_pg:photos_sr":0,
    "qs_pg:pop_sr":1,
    "qs_pg:qs_pg_placetype":"locality",
    "qs_pg:qs_pg_placetype_gp":"Town",
    "qs_pg:woe_adm0":23424881,
    "woe:adm0_id":23424881,
    "woe:name_adm0":"Luxembourg",
    "woe:name_adm1":"Grevenmacher",
    "woe:placetype":"Town",
    "wof:lang_x_official":[
        "fra",
        "ltz",
        "deu"
    ],
    "wof:lang_x_spoken":[
        "fra",
        "ltz",
        "deu"
    ],
    "wof:name":"Burmerange",
    "wof:placetype":"neighbourhood",
    "wof:population":191
},
  "geometry": {"coordinates":[6.32306,49.48528],"type":"Point"}
}