{
  "type": "Feature",
  "properties": {
    "gn:admin1_code":"ME",
    "gn:admin2_code":"3.0",
    "gn:asciiname":"Grevenknapp",
    "gn:cc2":"LU",
    "gn:country_code":"LU",
    "gn:dem":318,
    "gn:feature_class":"P",
    "gn:feature_code":"PPL",
    "gn:name":"Grevenknapp",
    "gn:population":0,
    "gn:timezone":"Europe/Luxembourg",
    "iso:country":"LU",
    "name:afr_x_preferred":[
        "Grevenknapp"
    ],
    "name:cat_x_preferred":[
        "Grevenknapp"
    ],
    "name:deu_x_preferred":[
        "Grevenknapp"
    ],
    "name:fra_x_preferred":[
        "Grevenknapp"
    ],
    "name:ltz_x_preferred":[
        "Gr\u00e9iweknapp"
    ],
    "name:msa_x_preferred":[
        "Grevenknapp"
    ],
    "name:nld_x_preferred":[
        "Grevenknapp"
    ],
    "name:pol_x_preferred":[
        "Grevenknapp"
    ],
    "name:und_x_variant":[
        "Groevenknapp",
        "Grevenknopp"
    ],
    "wof:lang_x_official":[
        "fra",
        "ltz",
        "deu"
    ],
    "wof:lang_x_spoken":[
        "fra",
        "ltz",
        "deu"
    ],
    "wof:name":"Grevenknapp",
    "wof:placetype":"neighbourhood"
},
  "geometry": {"coordinates":[6.03389,49.7625],"type":"Point"}
}