{
  "type": "Feature",
  "properties": {
    "iso:country":"LU",
    "name:cat_x_preferred":[
        "Howald"
    ],
    "name:deu_x_preferred":[
        "Howald"
    ],
    "name:eng_x_preferred":[
        "Howald"
    ],
    "name:fra_x_preferred":[
        "Howald"
    ],
    "name:hun_x_preferred":[
        "Howald"
    ],
    "name:ltz_x_preferred":[
        "Houwald"
    ],
    "name:nld_x_preferred":[
        "Howald"
    ],
    "name:pol_x_preferred":[
        "Howald"
    ],
    "qs:gn_adm0_cc":"LU",
    "qs:gn_fcode":"PPL",
    "qs:gn_local":7290933,
    "qs:gn_nam_loc":"howald",
    "qs:gn_namadm1":"03",
    "qs:gn_name":"Howald",
    "qs:local_max":428,
    "qs:local_sum":428,
    "qs:localhoods":1,
    "qs:name":"Howald",
    "qs:name_adm0":"Luxembourg",
    "qs:name_adm1":"Luxembourg",
    "qs:name_adm2":"Luxembourg",
    "qs:name_lau":"Hesperange",
    "qs:name_local":"Howald",
    "qs:photo_max":216,
    "qs:photo_sum":428,
    "qs:placetype":"Town",
    "qs:quad_count":26,
    "qs:woe_adm0":23424881,
    "qs:woe_adm1":20070560,
    "qs:woe_adm2":12591920,
    "qs:woe_funk":"Changed from suburb in 7.3.1",
    "qs:woe_lau":12591909,
    "qs:woe_local":979629,
    "qs:woe_ver":"7.10.0",
    "wd:wordcount":333,
    "wof:lang":[
        "unk"
    ],
    "wof:lang_x_official":[
        "fra",
        "ltz",
        "deu"
    ],
    "wof:lang_x_spoken":[
        "fra",
        "ltz",
        "deu"
    ],
    "wof:name":"Howald",
    "wof:placetype":"neighbourhood"
},
  "geometry": {"coordinates":[6.138518,49.583935],"type":"Point"}
}