{
  "type": "Feature",
  "properties": {
    "gn:country":"LU",
    "gn:fcode":"PPLX",
    "gn:population":402,
    "iso:country":"LU",
    "name:ara_x_preferred":[
        "\u0644\u0627\u0633\u0648\u0641\u0627\u062c"
    ],
    "name:arz_x_preferred":[
        "\u0644\u0627\u0633\u0648\u0641\u0627\u062c"
    ],
    "name:cat_x_preferred":[
        "Lasauvage"
    ],
    "name:ceb_x_preferred":[
        "Lasauvage"
    ],
    "name:deu_x_preferred":[
        "Lasauvage"
    ],
    "name:eng_x_preferred":[
        "Lasauvage"
    ],
    "name:fra_x_preferred":[
        "Lasauvage"
    ],
    "name:ltz_x_preferred":[
        "Zowaasch"
    ],
    "name:nld_x_preferred":[
        "Lasauvage"
    ],
    "name:pol_x_preferred":[
        "Lasauvage"
    ],
    "name:swe_x_preferred":[
        "Lasauvage"
    ],
    "name:szl_x_preferred":[
        "Lasauvage"
    ],
    "qs_pg:aaroncc":"LU",
    "qs_pg:gn_country":"LU",
    "qs_pg:gn_fcode":"PPLX",
    "qs_pg:gn_pop":402,
    "qs_pg:name":"Lasauvage",
    "qs_pg:name_adm0":"Luxembourg",
    "qs_pg:name_adm1":"Luxembourg",
    "qs_pg:photos":121,
    "qs_pg:photos_1k":25,
    "qs_pg:photos_9k":1,
    "qs_pg:photos_9r":0,
    "qs_pg:photos_all":121,
    "qs_pg:photos_sr":0,
    "qs_pg:pop_sr":2,
    "qs_pg:qs_pg_placetype":"neighbourhood",
    "qs_pg:qs_pg_placetype_gp":"Town",
    "qs_pg:woe_adm0":23424881,
    "woe:adm0_id":23424881,
    "woe:name_adm0":"Luxembourg",
    "woe:name_adm1":"Luxembourg",
    "woe:placetype":"Town",
    "wof:lang_x_official":[
        "fra",
        "ltz",
        "deu"
    ],
    "wof:lang_x_spoken":[
        "fra",
        "ltz",
        "deu"
    ],
    "wof:name":"Lasauvage",
    "wof:placetype":"neighbourhood",
    "wof:population":402
},
  "geometry": {"coordinates":[5.8375,49.525],"type":"Point"}
}