{
  "type": "Feature",
  "properties": {
    "gn:gn_country":"LU",
    "gn:gn_fcode":"ADM3",
    "gn:gn_pop":0,
    "iso:country":"LU",
    "name:als_x_preferred":[
        "Wanseler"
    ],
    "name:bel_x_preferred":[
        "\u0412\u0456\u043d\u0441\u0435\u043b\u0435\u0440"
    ],
    "name:cat_x_preferred":[
        "Winseler"
    ],
    "name:ceb_x_preferred":[
        "Winseler"
    ],
    "name:dan_x_preferred":[
        "Winseler"
    ],
    "name:deu_x_preferred":[
        "Winseler"
    ],
    "name:fas_x_preferred":[
        "\u0648\u06cc\u0646\u0632\u0644\u0631"
    ],
    "name:fra_x_preferred":[
        "Winseler"
    ],
    "name:ita_x_preferred":[
        "Winseler"
    ],
    "name:ltz_x_preferred":[
        "Gemeng Wanseler"
    ],
    "name:msa_x_preferred":[
        "Winseler"
    ],
    "name:nld_x_preferred":[
        "Winseler"
    ],
    "name:nor_x_preferred":[
        "Winseler"
    ],
    "name:pol_x_preferred":[
        "Winseler"
    ],
    "name:por_x_preferred":[
        "Winseler"
    ],
    "name:rus_x_preferred":[
        "\u0412\u0438\u043d\u0437\u0435\u043b\u0435\u0440"
    ],
    "name:slk_x_preferred":[
        "Winseler"
    ],
    "name:swe_x_preferred":[
        "Winseler"
    ],
    "name:ukr_x_preferred":[
        "\u0412\u0456\u043d\u0441\u0435\u043b\u0435\u0440"
    ],
    "qs_pg:aaroncc":"LU",
    "qs_pg:gn_country":"LU",
    "qs_pg:gn_fcode":"ADM3",
    "qs_pg:gn_pop":0,
    "qs_pg:name":"Winseler",
    "qs_pg:name_adm0":"Luxembourg",
    "qs_pg:name_adm1":"Diekirch",
    "qs_pg:photos":4,
    "qs_pg:photos_1k":1,
    "qs_pg:photos_9k":1,
    "qs_pg:photos_9r":2,
    "qs_pg:photos_all":46,
    "qs_pg:photos_sr":1,
    "qs_pg:pop_sr":0,
    "qs_pg:qs_pg_placetype":"localadmin",
    "qs_pg:qs_pg_placetype_gp":"LocalAdmin",
    "qs_pg:woe_adm0":23424881,
    "woe:adm0_id":23424881,
    "woe:name_adm0":"Luxembourg",
    "woe:name_adm1":"Diekirch",
    "woe:placetype":"LocalAdmin",
    "wof:name":"Winseler",
    "wof:placetype":"localadmin"
},
  "geometry": {"coordinates":[5.89028,49.96778],"type":"Point"}
}