{
  "type": "Feature",
  "properties": {
    "gn:gn_country":"LU",
    "gn:gn_fcode":"PPL",
    "gn:gn_pop":649,
    "gn:population":649,
    "iso:country":"LU",
    "name:cat_x_preferred":[
        "Perl\u00e9"
    ],
    "name:dut_x_preferred":[
        "Perl\u00e9"
    ],
    "name:eng_x_preferred":[
        "Perl\u00e9"
    ],
    "name:fre_x_preferred":[
        "Perl\u00e9"
    ],
    "name:ltz_x_preferred":[
        "P\u00e4rel"
    ],
    "name:swe_x_preferred":[
        "Perl\u00e9"
    ],
    "qs_pg:aaroncc":"LU",
    "qs_pg:gn_country":"LU",
    "qs_pg:gn_fcode":"PPL",
    "qs_pg:gn_pop":649,
    "qs_pg:name":"Perl\u00e9",
    "qs_pg:name_adm0":"Luxembourg",
    "qs_pg:name_adm1":"Diekirch",
    "qs_pg:photos":59,
    "qs_pg:photos_1k":12,
    "qs_pg:photos_9k":1,
    "qs_pg:photos_9r":2,
    "qs_pg:photos_all":59,
    "qs_pg:photos_sr":2,
    "qs_pg:pop_sr":2,
    "qs_pg:qs_pg_placetype":"locality",
    "qs_pg:qs_pg_placetype_gp":"Town",
    "qs_pg:woe_adm0":23424881,
    "woe:adm0_id":23424881,
    "woe:name_adm0":"Luxembourg",
    "woe:name_adm1":"Diekirch",
    "woe:placetype":"Town",
    "wof:name":"Perl\u00e9",
    "wof:placetype":"locality",
    "wof:population":649
},
  "geometry": {"coordinates":[5.76583,49.81167],"type":"Point"}
}