{
  "type": "Feature",
  "properties": {
    "gn:gn_country":"LU",
    "gn:gn_fcode":"PPL",
    "gn:gn_pop":413,
    "gn:population":413,
    "iso:country":"LU",
    "name:cat_x_preferred":[
        "Hunsdorf"
    ],
    "name:eng_x_preferred":[
        "Hunsdorf"
    ],
    "name:fra_x_preferred":[
        "Hunsdorf"
    ],
    "name:ltz_x_preferred":[
        "H\u00ebnsdref"
    ],
    "name:nld_x_preferred":[
        "H\u00fcnsdorf"
    ],
    "name:pol_x_preferred":[
        "Hunsdorf"
    ],
    "name:swe_x_preferred":[
        "Hunsdorf"
    ],
    "qs_pg:aaroncc":"LU",
    "qs_pg:gn_country":"LU",
    "qs_pg:gn_fcode":"PPL",
    "qs_pg:gn_pop":413,
    "qs_pg:name":"Hunsdorf",
    "qs_pg:name_adm0":"Luxembourg",
    "qs_pg:name_adm1":"Luxembourg",
    "qs_pg:photos_9k":1,
    "qs_pg:photos_9r":1,
    "qs_pg:photos_all":3,
    "qs_pg:photos_sr":0,
    "qs_pg:pop_sr":2,
    "qs_pg:qs_pg_placetype":"locality",
    "qs_pg:qs_pg_placetype_gp":"Town",
    "qs_pg:woe_adm0":23424881,
    "woe:adm0_id":23424881,
    "woe:name_adm0":"Luxembourg",
    "woe:name_adm1":"Luxembourg",
    "woe:placetype":"Town",
    "wof:name":"Hunsdorf",
    "wof:placetype":"locality",
    "wof:population":413
},
  "geometry": {"coordinates":[6.13167,49.69667],"type":"Point"}
}