{
  "type": "Feature",
  "properties": {
    "gn:admin1_code":"CA",
    "gn:asciiname":"Gaichel",
    "gn:cc2":"LU",
    "gn:country_code":"LU",
    "gn:dem":306,
    "gn:feature_class":"P",
    "gn:feature_code":"PPLL",
    "gn:name":"Gaichel",
    "gn:population":0,
    "gn:timezone":"Europe/Luxembourg",
    "iso:country":"LU",
    "name:und_x_variant":[
        "Fisbour",
        "S\u00e4gem\u00fchle",
        "Saegem\u00fchle",
        "Gaichel"
    ],
    "wof:name":"Gaichel",
    "wof:placetype":"locality"
},
  "geometry": {"coordinates":[5.86859,49.69467],"type":"Point"}
}