{
  "type": "Feature",
  "properties": {
    "gn:country":"LU",
    "gn:fcode":"PPL",
    "gn:population":192,
    "iso:country":"LU",
    "name:cat_x_preferred":[
        "Kahler"
    ],
    "name:ceb_x_preferred":[
        "Kahler"
    ],
    "name:deu_x_preferred":[
        "Kahler"
    ],
    "name:eng_x_preferred":[
        "Kahler"
    ],
    "name:fra_x_preferred":[
        "Kahler"
    ],
    "name:hun_x_preferred":[
        "Kahler"
    ],
    "name:ltz_x_preferred":[
        "Koler"
    ],
    "name:msa_x_preferred":[
        "Kahler"
    ],
    "name:nld_x_preferred":[
        "Kahler"
    ],
    "name:pol_x_preferred":[
        "Kahler"
    ],
    "name:swe_x_preferred":[
        "Kahler"
    ],
    "qs_pg:aaroncc":"LU",
    "qs_pg:gn_country":"LU",
    "qs_pg:gn_fcode":"PPL",
    "qs_pg:gn_pop":192,
    "qs_pg:name":"Kahler",
    "qs_pg:name_adm0":"Luxembourg",
    "qs_pg:name_adm1":"Luxembourg",
    "qs_pg:photos":33,
    "qs_pg:photos_1k":7,
    "qs_pg:photos_9k":1,
    "qs_pg:photos_9r":2,
    "qs_pg:photos_all":33,
    "qs_pg:photos_sr":2,
    "qs_pg:pop_sr":1,
    "qs_pg:qs_pg_placetype":"locality",
    "qs_pg:qs_pg_placetype_gp":"Town",
    "qs_pg:woe_adm0":23424881,
    "woe:adm0_id":23424881,
    "woe:name_adm0":"Luxembourg",
    "woe:name_adm1":"Luxembourg",
    "woe:placetype":"Town",
    "wof:lang_x_official":[
        "fra",
        "ltz",
        "deu"
    ],
    "wof:lang_x_spoken":[
        "fra",
        "ltz",
        "deu"
    ],
    "wof:name":"Kahler",
    "wof:placetype":"neighbourhood",
    "wof:population":192
},
  "geometry": {"coordinates":[5.91778,49.63139],"type":"Point"}
}