{
  "type": "Feature",
  "properties": {
    "gn:country":"LU",
    "gn:fcode":"PPL",
    "gn:population":231,
    "iso:country":"LU",
    "name:cat_x_preferred":[
        "Bettborn"
    ],
    "name:ceb_x_preferred":[
        "Bettborn"
    ],
    "name:deu_x_preferred":[
        "Bettborn"
    ],
    "name:eng_x_preferred":[
        "Bettborn"
    ],
    "name:fra_x_preferred":[
        "Bettborn"
    ],
    "name:ltz_x_preferred":[
        "Bieberech"
    ],
    "name:msa_x_preferred":[
        "Bettborn"
    ],
    "name:nld_x_preferred":[
        "Bettborn"
    ],
    "name:oci_x_preferred":[
        "Bettborn"
    ],
    "name:pol_x_preferred":[
        "Bettborn"
    ],
    "name:spa_x_preferred":[
        "Bettborn"
    ],
    "name:swe_x_preferred":[
        "Bettborn"
    ],
    "name:zho_x_preferred":[
        "\u8d1d\u7279\u535a\u5c14\u6069"
    ],
    "qs_pg:aaroncc":"LU",
    "qs_pg:gn_country":"LU",
    "qs_pg:gn_fcode":"PPL",
    "qs_pg:gn_pop":231,
    "qs_pg:name":"Bettborn",
    "qs_pg:name_adm0":"Luxembourg",
    "qs_pg:name_adm1":"Diekirch",
    "qs_pg:photos":27,
    "qs_pg:photos_1k":5,
    "qs_pg:photos_9k":1,
    "qs_pg:photos_9r":2,
    "qs_pg:photos_all":27,
    "qs_pg:photos_sr":2,
    "qs_pg:pop_sr":2,
    "qs_pg:qs_pg_placetype":"locality",
    "qs_pg:qs_pg_placetype_gp":"Town",
    "qs_pg:woe_adm0":23424881,
    "woe:adm0_id":23424881,
    "woe:name_adm0":"Luxembourg",
    "woe:name_adm1":"Diekirch",
    "woe:placetype":"Town",
    "wof:name":"Bettborn",
    "wof:placetype":"locality",
    "wof:population":231
},
  "geometry": {"coordinates":[5.94111,49.79528],"type":"Point"}
}