{
  "type": "Feature",
  "properties": {
    "gn:admin1_code":"ME",
    "gn:admin2_code":"3.0",
    "gn:asciiname":"Grevenknapp",
    "gn:cc2":"LU",
    "gn:country_code":"LU",
    "gn:dem":318,
    "gn:feature_class":"P",
    "gn:feature_code":"PPL",
    "gn:name":"Grevenknapp",
    "gn:population":0,
    "gn:timezone":"Europe/Luxembourg",
    "iso:country":"LU",
    "name:und_x_variant":[
        "Groevenknapp",
        "Grevenknopp",
        "Grevenknapp"
    ],
    "wof:name":"Grevenknapp",
    "wof:placetype":"locality"
},
  "geometry": {"coordinates":[6.03389,49.7625],"type":"Point"}
}