{
  "type": "Feature",
  "properties": {
    "gn:admin1_code":"ME",
    "gn:admin2_code":"1.0",
    "gn:asciiname":"Lellerhaff",
    "gn:cc2":"LU",
    "gn:country_code":"LU",
    "gn:dem":217,
    "gn:feature_class":"P",
    "gn:feature_code":"PPLL",
    "gn:name":"Lellerhaff",
    "gn:population":0,
    "gn:timezone":"Europe/Luxembourg",
    "iso:country":"LU",
    "name:und_x_variant":[
        "Fermes",
        "Lellingerhof",
        "Lellerhaff"
    ],
    "wof:name":"Lellerhaff",
    "wof:placetype":"locality"
},
  "geometry": {"coordinates":[6.08611,49.79944],"type":"Point"}
}