{
  "type": "Feature",
  "properties": {
    "gn:admin1_code":"ES",
    "gn:admin2_code":"3.0",
    "gn:asciiname":"Burange",
    "gn:country_code":"LU",
    "gn:dem":280,
    "gn:feature_class":"P",
    "gn:feature_code":"PPL",
    "gn:name":"Burange",
    "gn:population":0,
    "gn:timezone":"Europe/Luxembourg",
    "iso:country":"LU",
    "name:cat_x_preferred":[
        "Burange"
    ],
    "name:fra_x_preferred":[
        "Burange"
    ],
    "name:ltz_x_preferred":[
        "Bireng"
    ],
    "wof:lang_x_official":[
        "fra",
        "ltz",
        "deu"
    ],
    "wof:lang_x_spoken":[
        "fra",
        "ltz",
        "deu"
    ],
    "wof:name":"Burange",
    "wof:placetype":"neighbourhood"
},
  "geometry": {"coordinates":[6.0925,49.49111],"type":"Point"}
}