{
  "type": "Feature",
  "properties": {
    "gn:country":"LU",
    "gn:fcode":"PPL",
    "gn:population":116,
    "iso:country":"LU",
    "name:cat_x_preferred":[
        "Michelbouch"
    ],
    "name:ceb_x_preferred":[
        "Michelbouch"
    ],
    "name:eng_x_preferred":[
        "Michelbouch"
    ],
    "name:fra_x_preferred":[
        "Michelbouch"
    ],
    "name:ltz_x_preferred":[
        "M\u00e9chelbuch"
    ],
    "name:msa_x_preferred":[
        "Michelbouch"
    ],
    "name:nld_x_preferred":[
        "Michelbouch"
    ],
    "name:pol_x_preferred":[
        "Michelbouch"
    ],
    "name:swe_x_preferred":[
        "Michelbouch"
    ],
    "name:und_x_variant":[
        "Michelsberg"
    ],
    "qs_pg:aaroncc":"LU",
    "qs_pg:gn_country":"LU",
    "qs_pg:gn_fcode":"PPL",
    "qs_pg:gn_pop":116,
    "qs_pg:name":"Michelbuch",
    "qs_pg:name_adm0":"Luxembourg",
    "qs_pg:name_adm1":"Diekirch",
    "qs_pg:photos_9k":1,
    "qs_pg:photos_9r":1,
    "qs_pg:photos_all":2,
    "qs_pg:photos_sr":0,
    "qs_pg:pop_sr":1,
    "qs_pg:qs_pg_placetype":"locality",
    "qs_pg:qs_pg_placetype_gp":"Town",
    "qs_pg:woe_adm0":23424881,
    "woe:adm0_id":23424881,
    "woe:name_adm0":"Luxembourg",
    "woe:name_adm1":"Diekirch",
    "woe:placetype":"Town",
    "wof:lang_x_official":[
        "fra",
        "ltz",
        "deu"
    ],
    "wof:lang_x_spoken":[
        "fra",
        "ltz",
        "deu"
    ],
    "wof:name":"Michelbuch",
    "wof:placetype":"neighbourhood",
    "wof:population":116
},
  "geometry": {"coordinates":[6.02028,49.81861],"type":"Point"}
}