{
  "type": "Feature",
  "properties": {
    "gn:country":"LU",
    "gn:fcode":"PPL",
    "gn:population":863,
    "iso:country":"LU",
    "name:cat_x_preferred":[
        "Berchem"
    ],
    "name:ceb_x_preferred":[
        "Berchem"
    ],
    "name:deu_x_preferred":[
        "Berchem"
    ],
    "name:eng_x_preferred":[
        "Berchem"
    ],
    "name:fra_x_preferred":[
        "Berchem"
    ],
    "name:ita_x_preferred":[
        "Berchem"
    ],
    "name:ltz_x_preferred":[
        "Bierchem"
    ],
    "name:nld_x_preferred":[
        "Berchem"
    ],
    "name:pol_x_preferred":[
        "Berchem"
    ],
    "name:por_x_preferred":[
        "Berchem"
    ],
    "name:spa_x_preferred":[
        "Berchem"
    ],
    "name:swe_x_preferred":[
        "Berchem"
    ],
    "name:und_x_variant":[
        "Bercham"
    ],
    "qs_pg:aaroncc":"LU",
    "qs_pg:gn_country":"LU",
    "qs_pg:gn_fcode":"PPL",
    "qs_pg:gn_pop":863,
    "qs_pg:name":"Berchiwe",
    "qs_pg:name_adm0":"Belgique",
    "qs_pg:name_adm1":"Luxembourg",
    "qs_pg:photos_9r":0,
    "qs_pg:photos_sr":0,
    "qs_pg:pop_sr":2,
    "qs_pg:qs_pg_placetype":"locality",
    "qs_pg:qs_pg_placetype_gp":"Town",
    "qs_pg:woe_adm0":23424757,
    "woe:adm0_id":23424757,
    "woe:name_adm0":"Belgique",
    "woe:name_adm1":"Luxembourg",
    "woe:placetype":"Town",
    "wof:lang_x_official":[
        "fra",
        "ltz",
        "deu"
    ],
    "wof:lang_x_spoken":[
        "fra",
        "ltz",
        "deu"
    ],
    "wof:name":"Berchiwe",
    "wof:placetype":"neighbourhood",
    "wof:population":863
},
  "geometry": {"coordinates":[6.12917,49.54028],"type":"Point"}
}