{
  "type": "Feature",
  "properties": {
    "gn:country":"LU",
    "gn:fcode":"PPL",
    "gn:population":404,
    "iso:country":"LU",
    "name:cat_x_preferred":[
        "Cruchten"
    ],
    "name:ceb_x_preferred":[
        "Cruchten"
    ],
    "name:fra_x_preferred":[
        "Cruchten"
    ],
    "name:ltz_x_preferred":[
        "Kruuchten"
    ],
    "name:nld_x_preferred":[
        "Cruchten"
    ],
    "name:pol_x_preferred":[
        "Cruchten"
    ],
    "name:swe_x_preferred":[
        "Cruchten"
    ],
    "name:und_x_variant":[
        "Kruchten"
    ],
    "qs_pg:aaroncc":"LU",
    "qs_pg:gn_country":"LU",
    "qs_pg:gn_fcode":"PPL",
    "qs_pg:gn_pop":404,
    "qs_pg:name":"Cruchten",
    "qs_pg:name_adm0":"Luxembourg",
    "qs_pg:name_adm1":"Luxembourg",
    "qs_pg:photos":171,
    "qs_pg:photos_1k":35,
    "qs_pg:photos_9k":1,
    "qs_pg:photos_9r":4,
    "qs_pg:photos_all":171,
    "qs_pg:photos_sr":4,
    "qs_pg:pop_sr":2,
    "qs_pg:qs_pg_placetype":"locality",
    "qs_pg:qs_pg_placetype_gp":"Town",
    "qs_pg:woe_adm0":23424881,
    "woe:adm0_id":23424881,
    "woe:name_adm0":"Luxembourg",
    "woe:name_adm1":"Luxembourg",
    "woe:placetype":"Town",
    "wof:lang_x_official":[
        "fra",
        "ltz",
        "deu"
    ],
    "wof:lang_x_spoken":[
        "fra",
        "ltz",
        "deu"
    ],
    "wof:name":"Cruchten",
    "wof:placetype":"neighbourhood",
    "wof:population":404
},
  "geometry": {"coordinates":[6.13278,49.79194],"type":"Point"}
}