{
  "type": "Feature",
  "properties": {
    "gn:gn_country":"LU",
    "gn:gn_fcode":"ADM3",
    "gn:gn_pop":0,
    "iso:country":"LU",
    "name:als_x_preferred":[
        "Nidderanven"
    ],
    "name:bel_x_preferred":[
        "\u041d\u0456\u0434\u044d\u0440\u0430\u043d\u0432\u0435\u043d"
    ],
    "name:bul_x_preferred":[
        "\u041d\u0438\u0434\u0435\u0440\u0430\u043d\u0432\u0435\u043d"
    ],
    "name:cat_x_preferred":[
        "Niederanven"
    ],
    "name:ceb_x_preferred":[
        "Niederanven"
    ],
    "name:dan_x_preferred":[
        "Niederanven"
    ],
    "name:deu_x_preferred":[
        "Niederanven"
    ],
    "name:fas_x_preferred":[
        "\u0646\u06cc\u062f\u0631\u0622\u0646\u0648\u0646"
    ],
    "name:fra_x_preferred":[
        "Niederanven"
    ],
    "name:ita_x_preferred":[
        "Niederanven"
    ],
    "name:kor_x_preferred":[
        "\ub2c8\ub370\ub780\ud39c"
    ],
    "name:ltz_x_preferred":[
        "Gemeng Nidderaanwen"
    ],
    "name:msa_x_preferred":[
        "Niederanven"
    ],
    "name:nld_x_preferred":[
        "Niederanven"
    ],
    "name:nor_x_preferred":[
        "Niederanven"
    ],
    "name:pol_x_preferred":[
        "Niederanven"
    ],
    "name:por_x_preferred":[
        "Niederanven"
    ],
    "name:rus_x_preferred":[
        "\u041d\u0438\u0434\u0435\u0440\u0430\u043d\u0432\u0435\u043d"
    ],
    "name:slk_x_preferred":[
        "Niederanven"
    ],
    "name:swe_x_preferred":[
        "Niederanven"
    ],
    "name:tur_x_preferred":[
        "Niederanven"
    ],
    "name:ukr_x_preferred":[
        "\u041d\u0456\u0434\u0435\u0440\u0430\u043d\u0432\u0435\u043d"
    ],
    "qs_pg:aaroncc":"LU",
    "qs_pg:gn_country":"LU",
    "qs_pg:gn_fcode":"ADM3",
    "qs_pg:gn_pop":0,
    "qs_pg:name":"Niederanven",
    "qs_pg:name_adm0":"Luxembourg",
    "qs_pg:name_adm1":"Luxembourg",
    "qs_pg:photos":2,
    "qs_pg:photos_1k":1,
    "qs_pg:photos_9k":1,
    "qs_pg:photos_9r":4,
    "qs_pg:photos_all":204,
    "qs_pg:photos_sr":1,
    "qs_pg:pop_sr":0,
    "qs_pg:qs_pg_placetype":"localadmin",
    "qs_pg:qs_pg_placetype_gp":"LocalAdmin",
    "qs_pg:woe_adm0":23424881,
    "woe:adm0_id":23424881,
    "woe:name_adm0":"Luxembourg",
    "woe:name_adm1":"Luxembourg",
    "woe:placetype":"LocalAdmin",
    "wof:name":"Niederanven",
    "wof:placetype":"localadmin"
},
  "geometry": {"coordinates":[6.26,49.6475],"type":"Point"}
}