{
  "type": "Feature",
  "properties": {
    "gn:admin1_code":"DI",
    "gn:admin2_code":"6.0",
    "gn:asciiname":"Wilmeshof",
    "gn:country_code":"LU",
    "gn:dem":196,
    "gn:feature_class":"P",
    "gn:feature_code":"PPL",
    "gn:name":"Wilmeshof",
    "gn:population":0,
    "gn:timezone":"Europe/Luxembourg",
    "iso:country":"LU",
    "wof:lang_x_official":[
        "fra",
        "ltz",
        "deu"
    ],
    "wof:lang_x_spoken":[
        "fra",
        "ltz",
        "deu"
    ],
    "wof:name":"Wilmeshof",
    "wof:placetype":"neighbourhood"
},
  "geometry": {"coordinates":[6.11667,49.85],"type":"Point"}
}