{
  "type": "Feature",
  "properties": {
    "gn:gn_country":"LU",
    "gn:gn_fcode":"PPL",
    "gn:gn_pop":58,
    "gn:population":58,
    "iso:country":"LU",
    "name:cat_x_preferred":[
        "Kalborn"
    ],
    "name:deu_x_preferred":[
        "Kalborn"
    ],
    "name:eng_x_preferred":[
        "Kalborn"
    ],
    "name:fra_x_preferred":[
        "Kalborn"
    ],
    "name:ltz_x_preferred":[
        "Kaalber"
    ],
    "name:msa_x_preferred":[
        "Kalborn"
    ],
    "name:nld_x_preferred":[
        "Kalborn"
    ],
    "name:unk_x_variant":[
        "Kalborn"
    ],
    "qs_pg:aaroncc":"LU",
    "qs_pg:gn_country":"LU",
    "qs_pg:gn_fcode":"PPL",
    "qs_pg:gn_pop":58,
    "qs_pg:name":"Malborn",
    "qs_pg:name_adm0":"Deutschland",
    "qs_pg:name_adm1":"Rheinland-Pfalz",
    "qs_pg:photos_9k":1,
    "qs_pg:photos_9r":1,
    "qs_pg:photos_all":4,
    "qs_pg:photos_sr":0,
    "qs_pg:pop_sr":1,
    "qs_pg:qs_pg_placetype":"locality",
    "qs_pg:qs_pg_placetype_gp":"Town",
    "qs_pg:woe_adm0":23424829,
    "woe:adm0_id":23424829,
    "woe:name_adm0":"Deutschland",
    "woe:name_adm1":"Rheinland-Pfalz",
    "woe:placetype":"Town",
    "wof:name":"Malborn",
    "wof:placetype":"locality",
    "wof:population":58
},
  "geometry": {"coordinates":[6.11306,50.10278],"type":"Point"}
}