{
  "type": "Feature",
  "properties": {
    "gn:country":"LU",
    "gn:fcode":"PPL",
    "gn:population":576,
    "iso:country":"LU",
    "name:bel_x_preferred":[
        "\u0411\u0435\u0432\u0430\u043d\u0436-\u0441\u044e\u0440-\u0410\u0442\u044d\u0440"
    ],
    "name:cat_x_preferred":[
        "Boevange-sur-Attert"
    ],
    "name:ceb_x_preferred":[
        "Boevange-sur-Attert"
    ],
    "name:dan_x_preferred":[
        "Boevange-sur-Attert"
    ],
    "name:deu_x_preferred":[
        "B\u00f6wingen/Attert"
    ],
    "name:eng_x_preferred":[
        "Boevange-sur-Attert"
    ],
    "name:fas_x_preferred":[
        "\u0628\u0648\u0648\u0627\u0646\u0698-\u0627\u062a\u0631\u062a"
    ],
    "name:fra_x_preferred":[
        "Boevange-sur-Attert"
    ],
    "name:gsw_x_preferred":[
        "B\u00e9iwen-Atert"
    ],
    "name:hun_x_preferred":[
        "Boevange-sur-Attert"
    ],
    "name:hye_x_preferred":[
        "\u0532\u0575\u0578\u057e\u0561\u0576\u056a \u057d\u0575\u0578\u0582\u0580 \u0531\u057f\u057f\u0565\u0580"
    ],
    "name:ita_x_preferred":[
        "Boevange-sur-Attert"
    ],
    "name:ltz_x_preferred":[
        "Gemeng B\u00e9iwen-Atert"
    ],
    "name:msa_x_preferred":[
        "Boevange-sur-Attert"
    ],
    "name:nan_x_preferred":[
        "Boevange-sur-Attert"
    ],
    "name:nld_x_preferred":[
        "Boevange-sur-Attert"
    ],
    "name:nob_x_preferred":[
        "Boevange-sur-Attert"
    ],
    "name:pol_x_preferred":[
        "Boevange-sur-Attert"
    ],
    "name:por_x_preferred":[
        "Boevange-sur-Attert"
    ],
    "name:rus_x_preferred":[
        "\u0411\u0435\u0432\u0430\u043d\u0436-\u0441\u044e\u0440-\u0410\u0442\u0442\u0435\u0440"
    ],
    "name:slk_x_preferred":[
        "Boevange-sur-Attert"
    ],
    "name:swe_x_preferred":[
        "Boevange-sur-Attert"
    ],
    "name:ukr_x_preferred":[
        "\u0411\u0435\u0432\u0430\u043d\u0436-\u0441\u044e\u0440-\u0410\u0442\u0442\u0435\u0440\u0442"
    ],
    "name:und_x_variant":[
        "Bowen an der Attert"
    ],
    "qs_pg:aaroncc":"LU",
    "qs_pg:gn_country":"LU",
    "qs_pg:gn_fcode":"PPL",
    "qs_pg:gn_pop":576,
    "qs_pg:name":"Boevange-sur-Attert",
    "qs_pg:name_adm0":"Luxembourg",
    "qs_pg:name_adm1":"Luxembourg",
    "qs_pg:photos_9k":1,
    "qs_pg:photos_9r":1,
    "qs_pg:photos_all":10,
    "qs_pg:photos_sr":0,
    "qs_pg:pop_sr":2,
    "qs_pg:qs_pg_placetype":"locality",
    "qs_pg:qs_pg_placetype_gp":"Town",
    "qs_pg:woe_adm0":23424881,
    "woe:adm0_id":23424881,
    "woe:name_adm0":"Luxembourg",
    "woe:name_adm1":"Luxembourg",
    "woe:placetype":"Town",
    "wof:name":"Boevange-sur-Attert",
    "wof:placetype":"neighbourhood",
    "wof:population":576
},
  "geometry": {"coordinates":[6.01556,49.77528],"type":"Point"}
}