{
  "type": "Feature",
  "properties": {
    "gn:country":"LU",
    "gn:fcode":"ADM3",
    "gn:population":0,
    "iso:country":"LU",
    "name:als_x_preferred":[
        "Hiefenech"
    ],
    "name:bel_x_preferred":[
        "\u0425\u0435\u0444\u0456\u043d\u0433\u0435\u043d"
    ],
    "name:cat_x_preferred":[
        "Heffingen"
    ],
    "name:ceb_x_preferred":[
        "Heffingen"
    ],
    "name:dan_x_preferred":[
        "Heffingen"
    ],
    "name:deu_x_preferred":[
        "Heffingen"
    ],
    "name:fas_x_preferred":[
        "\u0647\u0641\u06cc\u0646\u06af\u0646"
    ],
    "name:fra_x_preferred":[
        "Heffingen"
    ],
    "name:ita_x_preferred":[
        "Heffingen"
    ],
    "name:ltz_x_preferred":[
        "Gemeng Hiefenech"
    ],
    "name:msa_x_preferred":[
        "Heffingen"
    ],
    "name:nds_x_preferred":[
        "Gemeen Heffingen"
    ],
    "name:nld_x_preferred":[
        "Heffingen"
    ],
    "name:nor_x_preferred":[
        "Heffingen"
    ],
    "name:pol_x_preferred":[
        "Heffingen"
    ],
    "name:por_x_preferred":[
        "Heffingen"
    ],
    "name:rus_x_preferred":[
        "\u0425\u0435\u0444\u0444\u0438\u043d\u0433\u0435\u043d"
    ],
    "name:slk_x_preferred":[
        "Heffingen"
    ],
    "name:swe_x_preferred":[
        "Heffingen"
    ],
    "name:ukr_x_preferred":[
        "\u0413\u0435\u0444\u0444\u0456\u043d\u0433\u0435\u043d"
    ],
    "qs_pg:aaroncc":"LU",
    "qs_pg:gn_country":"LU",
    "qs_pg:gn_fcode":"ADM3",
    "qs_pg:gn_pop":0,
    "qs_pg:name":"Heffingen",
    "qs_pg:name_adm0":"Luxembourg",
    "qs_pg:name_adm1":"Luxembourg",
    "qs_pg:photos":13,
    "qs_pg:photos_1k":3,
    "qs_pg:photos_9k":1,
    "qs_pg:photos_9r":2,
    "qs_pg:photos_all":43,
    "qs_pg:photos_sr":1,
    "qs_pg:pop_sr":0,
    "qs_pg:qs_pg_placetype":"localadmin",
    "qs_pg:qs_pg_placetype_gp":"LocalAdmin",
    "qs_pg:woe_adm0":23424881,
    "woe:adm0_id":23424881,
    "woe:name_adm0":"Luxembourg",
    "woe:name_adm1":"Luxembourg",
    "woe:placetype":"LocalAdmin",
    "wof:name":"Heffingen",
    "wof:placetype":"localadmin"
},
  "geometry": {"coordinates":[6.24139,49.7625],"type":"Point"}
}