{
  "type": "Feature",
  "properties": {
    "gn:admin1_code":"RM",
    "gn:admin2_code":"8.0",
    "gn:asciiname":"Ersange",
    "gn:country_code":"LU",
    "gn:dem":216,
    "gn:feature_class":"P",
    "gn:feature_code":"PPL",
    "gn:name":"Ersange",
    "gn:population":0,
    "gn:timezone":"Europe/Luxembourg",
    "iso:country":"LU",
    "name:cat_x_preferred":[
        "Ersange"
    ],
    "name:ceb_x_preferred":[
        "Ersange"
    ],
    "name:fra_x_preferred":[
        "Ersange"
    ],
    "name:ltz_x_preferred":[
        "Ierseng"
    ],
    "name:msa_x_preferred":[
        "Ersange"
    ],
    "name:pol_x_preferred":[
        "Ersange"
    ],
    "name:swe_x_preferred":[
        "Ersange"
    ],
    "wof:lang_x_official":[
        "fra",
        "ltz",
        "deu"
    ],
    "wof:lang_x_spoken":[
        "fra",
        "ltz",
        "deu"
    ],
    "wof:name":"Ersange",
    "wof:placetype":"neighbourhood"
},
  "geometry": {"coordinates":[6.27556,49.57444],"type":"Point"}
}