{
  "type": "Feature",
  "properties": {
    "gn:gn_country":"LU",
    "gn:gn_fcode":"PPL",
    "gn:gn_pop":228,
    "gn:population":228,
    "iso:country":"LU",
    "name:als_x_preferred":[
        "Iermsdr\u00ebf"
    ],
    "name:bar_x_preferred":[
        "Ermsdorf"
    ],
    "name:bel_x_preferred":[
        "\u042d\u0440\u043c\u0441\u0434\u043e\u0440\u0444"
    ],
    "name:cat_x_preferred":[
        "Ermsdorf"
    ],
    "name:ceb_x_preferred":[
        "Ermsdorf"
    ],
    "name:dan_x_preferred":[
        "Ermsdorf"
    ],
    "name:deu_x_preferred":[
        "Ermsdorf"
    ],
    "name:fra_x_preferred":[
        "Ermsdorf"
    ],
    "name:ita_x_preferred":[
        "Ermsdorf"
    ],
    "name:lim_x_preferred":[
        "Ermsdorf"
    ],
    "name:ltz_x_preferred":[
        "Iermsdref"
    ],
    "name:msa_x_preferred":[
        "Ermsdorf"
    ],
    "name:nld_x_preferred":[
        "Ermsdorf"
    ],
    "name:nor_x_preferred":[
        "Ermsdorf"
    ],
    "name:pol_x_preferred":[
        "Ermsdorf"
    ],
    "name:por_x_preferred":[
        "Ermsdorf"
    ],
    "name:rus_x_preferred":[
        "\u042d\u0440\u043c\u0441\u0434\u043e\u0440\u0444"
    ],
    "name:slk_x_preferred":[
        "Ermsdorf"
    ],
    "name:swe_x_preferred":[
        "Ermsdorf"
    ],
    "name:ukr_x_preferred":[
        "\u0415\u0440\u043c\u0441\u0434\u043e\u0440\u0444"
    ],
    "qs_pg:aaroncc":"LU",
    "qs_pg:gn_country":"LU",
    "qs_pg:gn_fcode":"PPL",
    "qs_pg:gn_pop":228,
    "qs_pg:name":"Ermsdorf",
    "qs_pg:name_adm0":"Luxembourg",
    "qs_pg:name_adm1":"Diekirch",
    "qs_pg:photos_9k":1,
    "qs_pg:photos_9r":1,
    "qs_pg:photos_all":1,
    "qs_pg:photos_sr":0,
    "qs_pg:pop_sr":2,
    "qs_pg:qs_pg_placetype":"locality",
    "qs_pg:qs_pg_placetype_gp":"Town",
    "qs_pg:woe_adm0":23424881,
    "woe:adm0_id":23424881,
    "woe:name_adm0":"Luxembourg",
    "woe:name_adm1":"Diekirch",
    "woe:placetype":"Town",
    "wof:name":"Ermsdorf",
    "wof:placetype":"locality",
    "wof:population":228
},
  "geometry": {"coordinates":[6.22278,49.82944],"type":"Point"}
}