{
  "type": "Feature",
  "properties": {
    "gn:gn_country":"LU",
    "gn:gn_fcode":"PPL",
    "gn:gn_pop":593,
    "gn:population":593,
    "iso:country":"LU",
    "name:cat_x_preferred":[
        "Bech-Kleinmacher"
    ],
    "name:dut_x_preferred":[
        "Bech-Kleinmacher"
    ],
    "name:eng_x_preferred":[
        "Bech-Kleinmacher"
    ],
    "name:fre_x_preferred":[
        "Bech-Kleinmacher"
    ],
    "name:ltz_x_preferred":[
        "Bech-Maacher"
    ],
    "name:pol_x_preferred":[
        "Bech-Kleinmacher"
    ],
    "name:swe_x_preferred":[
        "Bech-Kleinmacher"
    ],
    "name:unk_x_variant":[
        "Bech-Kleinmacher"
    ],
    "qs_pg:aaroncc":"LU",
    "qs_pg:gn_country":"LU",
    "qs_pg:gn_fcode":"PPL",
    "qs_pg:gn_pop":593,
    "qs_pg:name":"Kleinmacher",
    "qs_pg:name_adm0":"Luxembourg",
    "qs_pg:name_adm1":"Grevenmacher",
    "qs_pg:photos_9r":0,
    "qs_pg:photos_sr":0,
    "qs_pg:pop_sr":2,
    "qs_pg:qs_pg_placetype":"locality",
    "qs_pg:qs_pg_placetype_gp":"Town",
    "qs_pg:woe_adm0":23424881,
    "woe:adm0_id":23424881,
    "woe:name_adm0":"Luxembourg",
    "woe:name_adm1":"Grevenmacher",
    "woe:placetype":"Town",
    "wof:name":"Kleinmacher",
    "wof:placetype":"locality",
    "wof:population":593
},
  "geometry": {"coordinates":[6.355,49.53083],"type":"Point"}
}