{
  "type": "Feature",
  "properties": {
    "iso:country":"LU",
    "name:als_x_preferred":[
        "R\u00ebmeleng"
    ],
    "name:bel_x_preferred":[
        "\u0420\u0443\u043c\u0435\u043b\u0430\u043d\u0436"
    ],
    "name:cat_x_preferred":[
        "Rumelange"
    ],
    "name:ceb_x_preferred":[
        "Rumelange"
    ],
    "name:dan_x_preferred":[
        "Rumelange"
    ],
    "name:deu_x_preferred":[
        "R\u00fcmelingen"
    ],
    "name:diq_x_preferred":[
        "Rumelange"
    ],
    "name:eus_x_preferred":[
        "Rumelange"
    ],
    "name:fas_x_preferred":[
        "\u0631\u0648\u0645\u0644\u0627\u0646\u0698"
    ],
    "name:fra_x_preferred":[
        "Rumelange"
    ],
    "name:ita_x_preferred":[
        "Rumelange"
    ],
    "name:kat_x_preferred":[
        "\u10e0\u10d8\u10e3\u10db\u10d4\u10da\u10d0\u10dc\u10df\u10d8"
    ],
    "name:kor_x_preferred":[
        "\ub93c\uba5c\ub791\uc8fc"
    ],
    "name:lit_x_preferred":[
        "Riumelan\u017eas"
    ],
    "name:ltz_x_preferred":[
        "Gemeng R\u00ebmeleng"
    ],
    "name:msa_x_preferred":[
        "Rumelange"
    ],
    "name:nld_x_preferred":[
        "Rumelange"
    ],
    "name:nno_x_preferred":[
        "Rumelange"
    ],
    "name:nor_x_preferred":[
        "Rumelange"
    ],
    "name:pol_x_preferred":[
        "Rumelange"
    ],
    "name:por_x_preferred":[
        "Rumelange"
    ],
    "name:ron_x_preferred":[
        "Rumelange"
    ],
    "name:rus_x_preferred":[
        "\u0420\u044e\u043c\u0435\u043b\u0430\u043d\u0436"
    ],
    "name:slk_x_preferred":[
        "Rumelange"
    ],
    "name:srp_x_preferred":[
        "\u0420\u0443\u043c\u0435\u043b\u0430\u043d\u0436"
    ],
    "name:swe_x_preferred":[
        "Rumelange"
    ],
    "name:ukr_x_preferred":[
        "\u0420\u044e\u043c\u0435\u043b\u0430\u043d\u0436"
    ],
    "name:vol_x_preferred":[
        "Rumelange"
    ],
    "qs_pg:aaroncc":"LU",
    "qs_pg:name":"Rumelange",
    "qs_pg:name_adm0":"Luxembourg",
    "qs_pg:name_adm1":"Luxembourg",
    "qs_pg:photos":11,
    "qs_pg:photos_1k":2,
    "qs_pg:photos_9k":1,
    "qs_pg:photos_9r":2,
    "qs_pg:photos_all":44,
    "qs_pg:photos_sr":1,
    "qs_pg:pop_sr":0,
    "qs_pg:qs_pg_placetype":"localadmin",
    "qs_pg:qs_pg_placetype_gp":"LocalAdmin",
    "qs_pg:woe_adm0":23424881,
    "woe:adm0_id":23424881,
    "woe:name_adm0":"Luxembourg",
    "woe:name_adm1":"Luxembourg",
    "woe:placetype":"LocalAdmin",
    "wof:name":"Rumelange",
    "wof:placetype":"localadmin"
},
  "geometry": {"coordinates":[6.042003,49.465732],"type":"Point"}
}