{
  "type": "Feature",
  "properties": {
    "iso:country":"LU",
    "name:als_x_preferred":[
        "Beetebuerg"
    ],
    "name:bel_x_preferred":[
        "\u0411\u0435\u0442\u044d\u043c\u0431\u0443\u0440"
    ],
    "name:cat_x_preferred":[
        "Bettembourg"
    ],
    "name:ceb_x_preferred":[
        "Bettembourg"
    ],
    "name:dan_x_preferred":[
        "Bettemburg"
    ],
    "name:deu_x_preferred":[
        "Bettemburg"
    ],
    "name:fas_x_preferred":[
        "\u0628\u062a\u0645\u0628\u0648\u0631\u06af"
    ],
    "name:fra_x_preferred":[
        "Bettembourg"
    ],
    "name:hye_x_preferred":[
        "\u0532\u0565\u057f\u057f\u0561\u0574\u0562\u0578\u0582\u0580"
    ],
    "name:ita_x_preferred":[
        "Bettembourg"
    ],
    "name:lit_x_preferred":[
        "Betemb\u016bras"
    ],
    "name:ltz_x_preferred":[
        "Gemeng Beetebuerg"
    ],
    "name:msa_x_preferred":[
        "Bettembourg"
    ],
    "name:nld_x_preferred":[
        "Bettembourg"
    ],
    "name:nor_x_preferred":[
        "Bettemburg"
    ],
    "name:pol_x_preferred":[
        "Bettembourg"
    ],
    "name:por_x_preferred":[
        "Bettembourg"
    ],
    "name:rus_x_preferred":[
        "\u0411\u0435\u0442\u0442\u0430\u043c\u0431\u0443\u0440"
    ],
    "name:slk_x_preferred":[
        "Bettembourg"
    ],
    "name:spa_x_preferred":[
        "Bettembourg"
    ],
    "name:swa_x_preferred":[
        "Bettembourg"
    ],
    "name:swe_x_preferred":[
        "Bettembourg"
    ],
    "name:ukr_x_preferred":[
        "\u0411\u0435\u0442\u0442\u0435\u043c\u0431\u0443\u0440\u0433"
    ],
    "qs_pg:aaroncc":"LU",
    "qs_pg:name":"Bettembourg",
    "qs_pg:name_adm0":"Luxembourg",
    "qs_pg:name_adm1":"Luxembourg",
    "qs_pg:photos":1,
    "qs_pg:photos_1k":1,
    "qs_pg:photos_9k":2,
    "qs_pg:photos_9r":5,
    "qs_pg:photos_all":479,
    "qs_pg:photos_sr":1,
    "qs_pg:pop_sr":0,
    "qs_pg:qs_pg_placetype":"localadmin",
    "qs_pg:qs_pg_placetype_gp":"LocalAdmin",
    "qs_pg:woe_adm0":23424881,
    "woe:adm0_id":23424881,
    "woe:name_adm0":"Luxembourg",
    "woe:name_adm1":"Luxembourg",
    "woe:placetype":"LocalAdmin",
    "wof:name":"Bettembourg",
    "wof:placetype":"localadmin"
},
  "geometry": {"coordinates":[6.100673,49.515541],"type":"Point"}
}