{
  "type": "Feature",
  "properties": {
    "gn:gn_country":"LU",
    "gn:gn_fcode":"ADM3",
    "gn:gn_pop":0,
    "iso:country":"LU",
    "name:als_x_preferred":[
        "Biissen"
    ],
    "name:bel_x_preferred":[
        "\u0411\u0456\u0441\u044d\u043d"
    ],
    "name:bul_x_preferred":[
        "\u0411\u0438\u0441\u0435\u043d"
    ],
    "name:cat_x_preferred":[
        "Bissen"
    ],
    "name:ceb_x_preferred":[
        "Bissen"
    ],
    "name:dan_x_preferred":[
        "Bissen"
    ],
    "name:deu_x_preferred":[
        "Bissen"
    ],
    "name:fas_x_preferred":[
        "\u0628\u06cc\u0633\u0646"
    ],
    "name:fra_x_preferred":[
        "Bissen"
    ],
    "name:ita_x_preferred":[
        "Bissen"
    ],
    "name:lit_x_preferred":[
        "Bisenas"
    ],
    "name:ltz_x_preferred":[
        "Gemeng Biissen"
    ],
    "name:msa_x_preferred":[
        "Bissen"
    ],
    "name:nds_x_preferred":[
        "Gemeen Bissen"
    ],
    "name:nld_x_preferred":[
        "Bissen"
    ],
    "name:nor_x_preferred":[
        "Bissen"
    ],
    "name:pol_x_preferred":[
        "Bissen"
    ],
    "name:por_x_preferred":[
        "Bissen"
    ],
    "name:rus_x_preferred":[
        "\u0411\u0438\u0441\u0441\u0435\u043d"
    ],
    "name:slk_x_preferred":[
        "Bissen"
    ],
    "name:swe_x_preferred":[
        "Bissen"
    ],
    "name:ukr_x_preferred":[
        "\u0411\u0456\u0441\u0441\u0435\u043d"
    ],
    "qs_pg:aaroncc":"LU",
    "qs_pg:gn_country":"LU",
    "qs_pg:gn_fcode":"ADM3",
    "qs_pg:gn_pop":0,
    "qs_pg:name":"Bissen",
    "qs_pg:name_adm0":"Luxembourg",
    "qs_pg:name_adm1":"Luxembourg",
    "qs_pg:photos":2,
    "qs_pg:photos_1k":1,
    "qs_pg:photos_9k":1,
    "qs_pg:photos_9r":1,
    "qs_pg:photos_all":2,
    "qs_pg:photos_sr":1,
    "qs_pg:pop_sr":0,
    "qs_pg:qs_pg_placetype":"localadmin",
    "qs_pg:qs_pg_placetype_gp":"LocalAdmin",
    "qs_pg:woe_adm0":23424881,
    "woe:adm0_id":23424881,
    "woe:name_adm0":"Luxembourg",
    "woe:name_adm1":"Luxembourg",
    "woe:placetype":"LocalAdmin",
    "wof:name":"Bissen",
    "wof:placetype":"localadmin"
},
  "geometry": {"coordinates":[6.06944,49.7875],"type":"Point"}
}