{
  "type": "Feature",
  "properties": {
    "gn:gn_country":"LU",
    "gn:gn_fcode":"PPL",
    "gn:gn_pop":125,
    "gn:population":125,
    "iso:country":"LU",
    "name:cat_x_preferred":[
        "Koetschette"
    ],
    "name:eng_x_preferred":[
        "Koetschette"
    ],
    "name:fra_x_preferred":[
        "Koetschette"
    ],
    "name:ltz_x_preferred":[
        "Kietscht"
    ],
    "name:nld_x_preferred":[
        "Koetschette"
    ],
    "name:pol_x_preferred":[
        "Koetschette"
    ],
    "name:swe_x_preferred":[
        "Koetschette"
    ],
    "qs_pg:aaroncc":"LU",
    "qs_pg:gn_country":"LU",
    "qs_pg:gn_fcode":"PPL",
    "qs_pg:gn_pop":125,
    "qs_pg:name":"Koetschette",
    "qs_pg:photos_9r":0,
    "qs_pg:photos_sr":0,
    "qs_pg:pop_sr":1,
    "qs_pg:qs_pg_placetype":"locality",
    "wof:name":"Koetschette",
    "wof:placetype":"locality",
    "wof:population":125
},
  "geometry": {"coordinates":[5.84028,49.83806],"type":"Point"}
}