{
  "type": "Feature",
  "properties": {
    "gn:gn_country":"LU",
    "gn:gn_fcode":"ADM3",
    "gn:gn_pop":0,
    "iso:country":"LU",
    "name:als_x_preferred":[
        "B\u00e9iwen-Atert"
    ],
    "name:bel_x_preferred":[
        "\u0411\u0435\u0432\u0430\u043d\u0436-\u0441\u044e\u0440-\u0410\u0442\u044d\u0440"
    ],
    "name:deu_x_preferred":[
        "B\u00f6wingen/Attert"
    ],
    "name:fas_x_preferred":[
        "\u0628\u0648\u0648\u0627\u0646\u0698-\u0627\u062a\u0631\u062a"
    ],
    "name:hye_x_preferred":[
        "\u0532\u0575\u0578\u057e\u0561\u0576\u056a \u057d\u0575\u0578\u0582\u0580 \u0531\u057f\u057f\u0565\u0580"
    ],
    "name:ltz_x_preferred":[
        "Gemeng B\u00e9iwen-Atert"
    ],
    "name:rus_x_preferred":[
        "\u0411\u0451\u0432\u0430\u043d\u0436-\u0441\u044e\u0440-\u0410\u0442\u0442\u0435\u0440"
    ],
    "name:ukr_x_preferred":[
        "\u0411\u0435\u0432\u0430\u043d\u0436-\u0441\u044e\u0440-\u0410\u0442\u0442\u0435\u0440\u0442"
    ],
    "qs_pg:aaroncc":"LU",
    "qs_pg:gn_country":"LU",
    "qs_pg:gn_fcode":"ADM3",
    "qs_pg:gn_pop":0,
    "qs_pg:name":"Boevange-sur-Attert",
    "qs_pg:name_adm0":"Luxembourg",
    "qs_pg:name_adm1":"Luxembourg",
    "qs_pg:photos":17,
    "qs_pg:photos_1k":3,
    "qs_pg:photos_9k":1,
    "qs_pg:photos_9r":2,
    "qs_pg:photos_all":26,
    "qs_pg:photos_sr":1,
    "qs_pg:pop_sr":0,
    "qs_pg:qs_pg_placetype":"localadmin",
    "qs_pg:qs_pg_placetype_gp":"LocalAdmin",
    "qs_pg:woe_adm0":23424881,
    "woe:adm0_id":23424881,
    "woe:name_adm0":"Luxembourg",
    "woe:name_adm1":"Luxembourg",
    "woe:placetype":"LocalAdmin",
    "wof:name":"Boevange-sur-Attert",
    "wof:placetype":"localadmin"
},
  "geometry": {"coordinates":[6.01556,49.77528],"type":"Point"}
}