{
  "type": "Feature",
  "properties": {
    "gn:country":"LU",
    "gn:fcode":"PPL",
    "gn:population":802,
    "iso:country":"LU",
    "name:cat_x_preferred":[
        "Bofferdange"
    ],
    "name:ceb_x_preferred":[
        "Bofferdange"
    ],
    "name:eng_x_preferred":[
        "Bofferdange"
    ],
    "name:fra_x_preferred":[
        "Bofferdange"
    ],
    "name:ltz_x_preferred":[
        "Bouferdeng"
    ],
    "name:nld_x_preferred":[
        "Bofferdange"
    ],
    "name:pol_x_preferred":[
        "Bofferdange"
    ],
    "name:swe_x_preferred":[
        "Bofferdange"
    ],
    "qs_pg:aaroncc":"LU",
    "qs_pg:gn_country":"LU",
    "qs_pg:gn_fcode":"PPL",
    "qs_pg:gn_pop":802,
    "qs_pg:name":"Bofferdange",
    "qs_pg:name_adm0":"Luxembourg",
    "qs_pg:name_adm1":"Luxembourg",
    "qs_pg:photos_9r":0,
    "qs_pg:photos_sr":0,
    "qs_pg:pop_sr":2,
    "qs_pg:qs_pg_placetype":"locality",
    "qs_pg:qs_pg_placetype_gp":"Town",
    "qs_pg:woe_adm0":23424881,
    "woe:adm0_id":23424881,
    "woe:name_adm0":"Luxembourg",
    "woe:name_adm1":"Luxembourg",
    "woe:placetype":"Town",
    "wof:name":"Bofferdange",
    "wof:placetype":"locality",
    "wof:population":802
},
  "geometry": {"coordinates":[6.14167,49.68306],"type":"Point"}
}