{
  "type": "Feature",
  "properties": {
    "gn:gn_country":"LU",
    "gn:gn_fcode":"PPLL",
    "gn:gn_pop":108,
    "gn:population":108,
    "iso:country":"LU",
    "name:cat_x_preferred":[
        "Marienthal"
    ],
    "name:dut_x_preferred":[
        "Marienthal"
    ],
    "name:eng_x_preferred":[
        "Marienthal"
    ],
    "name:fre_x_preferred":[
        "Marienthal"
    ],
    "name:ger_x_preferred":[
        "Marienthal"
    ],
    "name:ltz_x_preferred":[
        "Mariendall"
    ],
    "name:pol_x_preferred":[
        "Marienthal"
    ],
    "name:swe_x_preferred":[
        "Marienthal"
    ],
    "qs_pg:aaroncc":"LU",
    "qs_pg:gn_country":"LU",
    "qs_pg:gn_fcode":"PPLL",
    "qs_pg:gn_pop":108,
    "qs_pg:name":"Marienthal",
    "qs_pg:photos_9r":0,
    "qs_pg:photos_sr":0,
    "qs_pg:pop_sr":1,
    "qs_pg:qs_pg_placetype":"locality",
    "wof:name":"Marienthal",
    "wof:placetype":"locality",
    "wof:population":108
},
  "geometry": {"coordinates":[6.06167,49.71],"type":"Point"}
}