{
  "type": "Feature",
  "properties": {
    "gn:admin1_code":"CA",
    "gn:admin2_code":"5.0",
    "gn:asciiname":"Heckenhof",
    "gn:country_code":"LU",
    "gn:dem":323,
    "gn:feature_class":"P",
    "gn:feature_code":"PPL",
    "gn:name":"Heckenhof",
    "gn:population":0,
    "gn:timezone":"Europe/Luxembourg",
    "iso:country":"LU",
    "wof:name":"Heckenhof",
    "wof:placetype":"locality"
},
  "geometry": {"coordinates":[5.93333,49.68333],"type":"Point"}
}