{
  "type": "Feature",
  "properties": {
    "gn:admin1_code":"WI",
    "gn:admin2_code":"11.0",
    "gn:asciiname":"Weidingen",
    "gn:country_code":"LU",
    "gn:dem":320,
    "gn:feature_class":"P",
    "gn:feature_code":"PPL",
    "gn:name":"Weidingen",
    "gn:population":0,
    "gn:timezone":"Europe/Luxembourg",
    "iso:country":"LU",
    "name:cat_x_preferred":[
        "Weidingen"
    ],
    "name:fra_x_preferred":[
        "Weidingen"
    ],
    "name:ltz_x_preferred":[
        "Wegdichen"
    ],
    "name:msa_x_preferred":[
        "Weidingen"
    ],
    "name:pol_x_preferred":[
        "Weidingen"
    ],
    "wof:name":"Weidingen",
    "wof:placetype":"locality"
},
  "geometry": {"coordinates":[5.93884,49.97068],"type":"Point"}
}