{
  "type": "Feature",
  "properties": {
    "gn:gn_country":"LU",
    "gn:gn_fcode":"PPL",
    "gn:gn_pop":2489,
    "gn:population":2489,
    "iso:country":"LU",
    "name:bel_x_preferred":[
        "\u0421\u0430\u043d\u0435\u043c"
    ],
    "name:cat_x_preferred":[
        "Sanem"
    ],
    "name:dan_x_preferred":[
        "Sanem"
    ],
    "name:deu_x_preferred":[
        "Sanem"
    ],
    "name:dut_x_preferred":[
        "Sanem"
    ],
    "name:eng_x_preferred":[
        "Sanem"
    ],
    "name:fra_x_preferred":[
        "Sanem"
    ],
    "name:fre_x_preferred":[
        "Sanem"
    ],
    "name:ger_x_preferred":[
        "Sassenheim"
    ],
    "name:gsw_x_preferred":[
        "Suessem"
    ],
    "name:hun_x_preferred":[
        "Sanem"
    ],
    "name:ita_x_preferred":[
        "Sanem"
    ],
    "name:lit_x_preferred":[
        "Sanemas"
    ],
    "name:ltz_x_preferred":[
        "Suessem"
    ],
    "name:may_x_preferred":[
        "Sanem"
    ],
    "name:nan_x_preferred":[
        "Sanem"
    ],
    "name:nld_x_preferred":[
        "Sanem"
    ],
    "name:nob_x_preferred":[
        "Sanem"
    ],
    "name:per_x_preferred":[
        "\u0632\u0627\u0646\u0645"
    ],
    "name:pol_x_preferred":[
        "Sanem"
    ],
    "name:por_x_preferred":[
        "Sanem"
    ],
    "name:rus_x_preferred":[
        "\u0421\u0430\u043d\u0435\u043c"
    ],
    "name:slo_x_preferred":[
        "Sanem"
    ],
    "name:swa_x_preferred":[
        "Sanem"
    ],
    "name:swe_x_preferred":[
        "Sanem"
    ],
    "name:ukr_x_preferred":[
        "\u0421\u0430\u043d\u0435\u043c"
    ],
    "name:unk_x_variant":[
        "Sassenheim"
    ],
    "qs_pg:aaroncc":"LU",
    "qs_pg:gn_country":"LU",
    "qs_pg:gn_fcode":"PPL",
    "qs_pg:gn_pop":2489,
    "qs_pg:name":"Sanem",
    "qs_pg:name_adm0":"Luxembourg",
    "qs_pg:name_adm1":"Luxembourg",
    "qs_pg:photos":26,
    "qs_pg:photos_1k":5,
    "qs_pg:photos_9k":1,
    "qs_pg:photos_9r":2,
    "qs_pg:photos_all":26,
    "qs_pg:photos_sr":2,
    "qs_pg:pop_sr":4,
    "qs_pg:qs_pg_placetype":"locality",
    "qs_pg:qs_pg_placetype_gp":"Town",
    "qs_pg:woe_adm0":23424881,
    "woe:adm0_id":23424881,
    "woe:name_adm0":"Luxembourg",
    "woe:name_adm1":"Luxembourg",
    "woe:placetype":"Town",
    "wof:name":"Sanem",
    "wof:placetype":"locality",
    "wof:population":2489
},
  "geometry": {"coordinates":[5.92889,49.54806],"type":"Point"}
}