{
  "type": "Feature",
  "properties": {
    "gn:gn_country":"LU",
    "gn:gn_fcode":"PPL",
    "gn:gn_pop":38,
    "gn:population":38,
    "iso:country":"LU",
    "name:deu_x_preferred":[
        "Putscheid"
    ],
    "name:eng_x_preferred":[
        "Putscheid"
    ],
    "name:fra_x_preferred":[
        "Putscheid"
    ],
    "name:ltz_x_preferred":[
        "P\u00ebtscht"
    ],
    "name:nld_x_preferred":[
        "Putscheid"
    ],
    "name:pol_x_preferred":[
        "Putscheid"
    ],
    "name:por_x_preferred":[
        "Putscheid"
    ],
    "name:unk_x_variant":[
        "Putscheid"
    ],
    "qs_pg:aaroncc":"LU",
    "qs_pg:gn_country":"LU",
    "qs_pg:gn_fcode":"PPL",
    "qs_pg:gn_pop":38,
    "qs_pg:name":"Utscheid",
    "qs_pg:name_adm0":"Deutschland",
    "qs_pg:name_adm1":"Rheinland-Pfalz",
    "qs_pg:photos_9r":0,
    "qs_pg:photos_sr":0,
    "qs_pg:pop_sr":1,
    "qs_pg:qs_pg_placetype":"locality",
    "qs_pg:qs_pg_placetype_gp":"Town",
    "qs_pg:woe_adm0":23424829,
    "woe:adm0_id":23424829,
    "woe:name_adm0":"Deutschland",
    "woe:name_adm1":"Rheinland-Pfalz",
    "woe:placetype":"Town",
    "wof:name":"Utscheid",
    "wof:placetype":"locality",
    "wof:population":38
},
  "geometry": {"coordinates":[6.14306,49.96083],"type":"Point"}
}