{
  "type": "Feature",
  "properties": {
    "gn:gn_country":"LU",
    "gn:gn_fcode":"PPL",
    "gn:gn_pop":268,
    "gn:population":268,
    "iso:country":"LU",
    "name:cat_x_preferred":[
        "Wilwerdange"
    ],
    "name:eng_x_preferred":[
        "Wilwerdange"
    ],
    "name:fra_x_preferred":[
        "Wilwerdange"
    ],
    "name:jpn_x_preferred":[
        "\u30f4\u30a3\u30eb\u30f4\u30a7\u30eb\u30c0\u30f3\u30b8\u30e5"
    ],
    "name:ltz_x_preferred":[
        "Wilwerdang"
    ],
    "name:nld_x_preferred":[
        "Wilwerdange"
    ],
    "name:pol_x_preferred":[
        "Wilwerdange"
    ],
    "name:spa_x_preferred":[
        "Wilwerdange"
    ],
    "name:swe_x_preferred":[
        "Wilwerdange"
    ],
    "qs_pg:aaroncc":"LU",
    "qs_pg:gn_country":"LU",
    "qs_pg:gn_fcode":"PPL",
    "qs_pg:gn_pop":268,
    "qs_pg:name":"Wilwerdange",
    "qs_pg:name_adm0":"Luxembourg",
    "qs_pg:name_adm1":"Diekirch",
    "qs_pg:photos_9k":1,
    "qs_pg:photos_9r":1,
    "qs_pg:photos_all":4,
    "qs_pg:photos_sr":0,
    "qs_pg:pop_sr":2,
    "qs_pg:qs_pg_placetype":"locality",
    "qs_pg:qs_pg_placetype_gp":"Town",
    "qs_pg:woe_adm0":23424881,
    "woe:adm0_id":23424881,
    "woe:name_adm0":"Luxembourg",
    "woe:name_adm1":"Diekirch",
    "woe:placetype":"Town",
    "wof:name":"Wilwerdange",
    "wof:placetype":"locality",
    "wof:population":268
},
  "geometry": {"coordinates":[6.02389,50.14056],"type":"Point"}
}