{
  "type": "Feature",
  "properties": {
    "gn:admin1_code":"CL",
    "gn:admin2_code":"10.0",
    "gn:asciiname":"Hubertsmuhle",
    "gn:country_code":"LU",
    "gn:dem":501,
    "gn:feature_class":"P",
    "gn:feature_code":"PPL",
    "gn:name":"Hubertsmuhle",
    "gn:population":0,
    "gn:timezone":"Europe/Luxembourg",
    "iso:country":"LU",
    "wof:name":"Hubertsmuhle",
    "wof:placetype":"neighbourhood"
},
  "geometry": {"coordinates":[6.06667,50.13333],"type":"Point"}
}