{
  "type": "Feature",
  "properties": {
    "gn:gn_country":"LU",
    "gn:gn_fcode":"ADM3",
    "gn:gn_pop":0,
    "iso:country":"LU",
    "name:als_x_preferred":[
        "Noumer"
    ],
    "name:bel_x_preferred":[
        "\u041d\u043e\u043c\u0435\u0440\u043d"
    ],
    "name:cat_x_preferred":[
        "Nommern"
    ],
    "name:ceb_x_preferred":[
        "Nommern"
    ],
    "name:dan_x_preferred":[
        "Nommern"
    ],
    "name:deu_x_preferred":[
        "Nommern"
    ],
    "name:fas_x_preferred":[
        "\u0646\u0648\u0645\u0631\u0646"
    ],
    "name:fra_x_preferred":[
        "Nommern"
    ],
    "name:ita_x_preferred":[
        "Nommern"
    ],
    "name:ltz_x_preferred":[
        "Gemeng Noumer"
    ],
    "name:msa_x_preferred":[
        "Nommern"
    ],
    "name:nds_x_preferred":[
        "Gemeen Nommern"
    ],
    "name:nld_x_preferred":[
        "Nommern"
    ],
    "name:nor_x_preferred":[
        "Nommern"
    ],
    "name:pol_x_preferred":[
        "Nommern"
    ],
    "name:por_x_preferred":[
        "Nommern"
    ],
    "name:rus_x_preferred":[
        "\u041d\u043e\u043c\u043c\u0435\u0440\u043d"
    ],
    "name:slk_x_preferred":[
        "Nommern"
    ],
    "name:swe_x_preferred":[
        "Nommern"
    ],
    "name:ukr_x_preferred":[
        "\u041d\u043e\u043c\u043c\u0435\u0440\u043d"
    ],
    "qs_pg:aaroncc":"LU",
    "qs_pg:gn_country":"LU",
    "qs_pg:gn_fcode":"ADM3",
    "qs_pg:gn_pop":0,
    "qs_pg:name":"Nommern",
    "qs_pg:name_adm0":"Luxembourg",
    "qs_pg:name_adm1":"Luxembourg",
    "qs_pg:photos":2,
    "qs_pg:photos_1k":1,
    "qs_pg:photos_9k":1,
    "qs_pg:photos_9r":5,
    "qs_pg:photos_all":320,
    "qs_pg:photos_sr":1,
    "qs_pg:pop_sr":0,
    "qs_pg:qs_pg_placetype":"localadmin",
    "qs_pg:qs_pg_placetype_gp":"LocalAdmin",
    "qs_pg:woe_adm0":23424881,
    "woe:adm0_id":23424881,
    "woe:name_adm0":"Luxembourg",
    "woe:name_adm1":"Luxembourg",
    "woe:placetype":"LocalAdmin",
    "wof:name":"Nommern",
    "wof:placetype":"localadmin"
},
  "geometry": {"coordinates":[6.17472,49.78694],"type":"Point"}
}