{
  "type": "Feature",
  "properties": {
    "gn:admin1_code":"CL",
    "gn:admin2_code":"63.0",
    "gn:asciiname":"Dasbourg-Pont",
    "gn:country_code":"LU",
    "gn:dem":292,
    "gn:elevation":"273.0",
    "gn:feature_class":"P",
    "gn:feature_code":"PPLL",
    "gn:name":"Dasbourg-Pont",
    "gn:population":0,
    "gn:timezone":"Europe/Luxembourg",
    "iso:country":"LU",
    "wof:lang_x_official":[
        "fra",
        "ltz",
        "deu"
    ],
    "wof:lang_x_spoken":[
        "fra",
        "ltz",
        "deu"
    ],
    "wof:name":"Dasbourg-Pont",
    "wof:placetype":"neighbourhood"
},
  "geometry": {"coordinates":[6.12588,50.04922],"type":"Point"}
}