{
  "type": "Feature",
  "properties": {
    "gn:admin1_code":"WI",
    "gn:admin2_code":"2.0",
    "gn:asciiname":"Buurgfried",
    "gn:cc2":"LU",
    "gn:country_code":"LU",
    "gn:dem":329,
    "gn:feature_class":"P",
    "gn:feature_code":"PPLL",
    "gn:name":"Buurgfried",
    "gn:population":0,
    "gn:timezone":"Europe/Luxembourg",
    "iso:country":"LU",
    "name:und_x_variant":[
        "Burgfried",
        "Bourgfried",
        "Buurgfried"
    ],
    "wof:name":"Buurgfried",
    "wof:placetype":"locality"
},
  "geometry": {"coordinates":[5.85861,49.90083],"type":"Point"}
}