{
  "type": "Feature",
  "properties": {
    "gn:country":"LU",
    "gn:fcode":"PPL",
    "gn:population":1535,
    "iso:country":"LU",
    "name:cat_x_preferred":[
        "Bergem"
    ],
    "name:ceb_x_preferred":[
        "Bergem"
    ],
    "name:deu_x_preferred":[
        "Bergem"
    ],
    "name:eng_x_preferred":[
        "Bergem"
    ],
    "name:fra_x_preferred":[
        "Bergem"
    ],
    "name:ltz_x_preferred":[
        "Biergem"
    ],
    "name:nld_x_preferred":[
        "Bergem"
    ],
    "name:pol_x_preferred":[
        "Bergem"
    ],
    "name:swe_x_preferred":[
        "Bergem"
    ],
    "qs_pg:aaroncc":"LU",
    "qs_pg:gn_country":"LU",
    "qs_pg:gn_fcode":"PPL",
    "qs_pg:gn_pop":1535,
    "qs_pg:name":"Bergem",
    "qs_pg:photos_9r":0,
    "qs_pg:photos_sr":0,
    "qs_pg:pop_sr":3,
    "qs_pg:qs_pg_placetype":"locality",
    "wof:name":"Bergem",
    "wof:placetype":"neighbourhood",
    "wof:population":1535
},
  "geometry": {"coordinates":[6.04222,49.525],"type":"Point"}
}