{
  "type": "Feature",
  "properties": {
    "gn:admin1_code":"DI",
    "gn:admin2_code":"3.0",
    "gn:asciiname":"Scheidel",
    "gn:country_code":"LU",
    "gn:dem":453,
    "gn:feature_class":"P",
    "gn:feature_code":"PPL",
    "gn:name":"Scheidel",
    "gn:population":0,
    "gn:timezone":"Europe/Luxembourg",
    "iso:country":"LU",
    "name:deu_x_preferred":[
        "Scheidl"
    ],
    "name:fra_x_preferred":[
        "Scheidel"
    ],
    "wof:lang_x_official":[
        "fra",
        "ltz",
        "deu"
    ],
    "wof:lang_x_spoken":[
        "fra",
        "ltz",
        "deu"
    ],
    "wof:name":"Scheidel",
    "wof:placetype":"neighbourhood"
},
  "geometry": {"coordinates":[6.04472,49.89361],"type":"Point"}
}